<?xml version="1.0"?>
<GlideProfile>
  <MinLevel>1</MinLevel>
  <MaxLevel>80</MaxLevel>
  <NaturalRun>True</NaturalRun>
  <LureMinutes>0</LureMinutes>
  <SkipWaypoints>True</SkipWaypoints>
  <Factions></Factions>
  <Waypoint>3179.025 -1615.533 101.887</Waypoint>
  <Waypoint>3163.555 -1616.162 99.91129</Waypoint>
  <Waypoint>3099.769 -1614.14 91.75853</Waypoint>
  <Waypoint>3036.01 -1610.777 90.03839</Waypoint>
  <Waypoint>2971.832 -1607.397 88.4678</Waypoint>
  <Waypoint>2908.672 -1604.071 86.92216</Waypoint>
  <Waypoint>2844.302 -1600.681 85.34689</Waypoint>
  <Waypoint>2783.406 -1597.474 83.85663</Waypoint>
  <Waypoint>2730.495 -1610.704 82.49348</Waypoint>
  <Waypoint>2705.326 -1666.871 80.81604</Waypoint>
  <Waypoint>2746.01 -1714.269 80.7217</Waypoint>
  <Waypoint>2804.999 -1736.191 90.75468</Waypoint>
  <Waypoint>2868.656 -1743.016 99.51427</Waypoint>
  <Waypoint>2931.721 -1734.841 108.0043</Waypoint>
  <Waypoint>2994.356 -1726.529 116.4349</Waypoint>
  <Waypoint>3057.805 -1718.226 124.7221</Waypoint>
  <Waypoint>3119.099 -1713.405 142.0135</Waypoint>
  <Waypoint>3180.956 -1709.124 160.4982</Waypoint>
  <Waypoint>3241.287 -1719.035 176.973</Waypoint>
  <Waypoint>3298.745 -1743.005 190.0407</Waypoint>
  <Waypoint>3358.892 -1761.829 202.1411</Waypoint>
  <Waypoint>3421.155 -1763.997 216.0947</Waypoint>
  <Waypoint>3483.686 -1765.324 230.5346</Waypoint>
  <Waypoint>3541.523 -1766.552 243.8903</Waypoint>
  <Waypoint>3607.133 -1767.944 259.0411</Waypoint>
  <Waypoint>3669.416 -1769.266 273.4236</Waypoint>
  <Waypoint>3731.542 -1771.212 288.0229</Waypoint>
  <Waypoint>3793.737 -1777.438 304.3627</Waypoint>
  <Waypoint>3856.639 -1783.734 320.8882</Waypoint>
  <Waypoint>3918.657 -1785.171 331.8581</Waypoint>
  <Waypoint>3975.702 -1755.426 327.3057</Waypoint>
  <Waypoint>4023.904 -1713.371 322.4506</Waypoint>
  <Waypoint>4071.695 -1671.04 317.5382</Waypoint>
  <Waypoint>4133.092 -1660.867 314.4497</Waypoint>
  <Waypoint>4197.372 -1661.727 314.0571</Waypoint>
  <Waypoint>4259.688 -1674.086 312.4533</Waypoint>
  <Waypoint>4321.482 -1691.169 305.5098</Waypoint>
  <Waypoint>4381.267 -1708.386 297.8152</Waypoint>
  <Waypoint>4444.253 -1726.525 289.9994</Waypoint>
  <Waypoint>4500.93 -1755.507 285.7347</Waypoint>
  <Waypoint>4540.362 -1803.29 285.8916</Waypoint>
  <Waypoint>4550.661 -1867.573 279.3297</Waypoint>
  <Waypoint>4549.437 -1931.049 269.1453</Waypoint>
  <Waypoint>4540.345 -1993.799 263.2727</Waypoint>
  <Waypoint>4481.48 -2002.768 255.6573</Waypoint>
  <Waypoint>4423.978 -1974.977 260.2381</Waypoint>
  <Waypoint>4367.615 -1944.452 265.5642</Waypoint>
  <Waypoint>4311.448 -1914.032 270.8719</Waypoint>
  <Waypoint>4254.946 -1883.431 276.2113</Waypoint>
  <Waypoint>4198.416 -1852.815 281.5534</Waypoint>
  <Waypoint>4145.45 -1818.879 292.1614</Waypoint>
  <Waypoint>4091.145 -1784.596 304.8776</Waypoint>
  <Waypoint>4035.237 -1755.977 314.5163</Waypoint>
  <Waypoint>3972.748 -1742.366 321.6458</Waypoint>
  <Waypoint>3910.647 -1726.933 321.7717</Waypoint>
  <Waypoint>3848.324 -1712.618 313.4806</Waypoint>
  <Waypoint>3787.444 -1703.271 296.4793</Waypoint>
  <Waypoint>3726.295 -1700.378 276.0611</Waypoint>
  <Waypoint>3665.812 -1721.267 268.1157</Waypoint>
  <Waypoint>3607.565 -1746.781 261.237</Waypoint>
  <Waypoint>3548.506 -1771.264 253.0408</Waypoint>
  <Waypoint>3488.554 -1792.485 244.1028</Waypoint>
  <Waypoint>3427.725 -1808.265 233.6748</Waypoint>
  <Waypoint>3365.349 -1820.587 222.6241</Waypoint>
  <Waypoint>3302.764 -1829.959 211.8639</Waypoint>
  <Waypoint>3240.268 -1841.108 200.7809</Waypoint>
  <Waypoint>3177.601 -1852.706 189.2669</Waypoint>
  <Waypoint>3115.734 -1863.059 177.4842</Waypoint>
  <Waypoint>3053.074 -1871.112 165.4992</Waypoint>
  <Waypoint>2990.872 -1875.946 148.7957</Waypoint>
  <Waypoint>2929.467 -1873.974 130.8868</Waypoint>
  <Waypoint>2867.127 -1870.022 115.6138</Waypoint>
  <Waypoint>2803.684 -1864.486 108.4364</Waypoint>
  <Waypoint>2740.525 -1854.508 103.6037</Waypoint>
  <Waypoint>2677.791 -1842.184 99.5254</Waypoint>
  <Waypoint>2615.431 -1829.933 95.47149</Waypoint>
  <Waypoint>2552.822 -1817.633 91.40132</Waypoint>
  <Waypoint>2488.949 -1820.338 85.32916</Waypoint>
  <Waypoint>2430.133 -1843.844 80.36784</Waypoint>
  <Waypoint>2398.626 -1897.922 76.89082</Waypoint>
  <Waypoint>2421.477 -1956.312 74.05582</Waypoint>
  <Waypoint>2473.979 -1992.203 72.52516</Waypoint>
  <Waypoint>2537.714 -1996.271 75.84278</Waypoint>
  <Waypoint>2601.707 -1991.59 81.51295</Waypoint>
  <Waypoint>2665.225 -1986.943 87.14098</Waypoint>
  <Waypoint>2728.493 -1985.311 97.63844</Waypoint>
  <Waypoint>2791.486 -1986.555 112.2163</Waypoint>
  <Waypoint>2853.185 -1988.005 126.1333</Waypoint>
  <Waypoint>2916.881 -1989.607 140.3174</Waypoint>
  <Waypoint>2979.986 -1991.195 154.3697</Waypoint>
  <Waypoint>3042.654 -1992.699 167.8807</Waypoint>
  <Waypoint>3106.101 -1992.412 180.2256</Waypoint>
  <Waypoint>3165.574 -1992.752 191.4855</Waypoint>
  <Waypoint>3227.805 -2001.162 204.1427</Waypoint>
  <Waypoint>3290.349 -2009.664 217.1566</Waypoint>
  <Waypoint>3352.065 -2015.504 230.1018</Waypoint>
  <Waypoint>3411.458 -1992.227 243.3251</Waypoint>
  <Waypoint>3463.316 -1967.427 254.2386</Waypoint>
  <Waypoint>3525.019 -1937.919 267.2241</Waypoint>
  <Waypoint>3587.415 -1924.827 275.8787</Waypoint>
  <Waypoint>3650.674 -1922.35 285.3515</Waypoint>
  <Waypoint>3713.296 -1922.935 296.9365</Waypoint>
  <Waypoint>3776.64 -1923.533 308.7916</Waypoint>
  <Waypoint>3839.67 -1924.129 320.588</Waypoint>
  <Waypoint>3902.509 -1925.336 328.9505</Waypoint>
  <Waypoint>3967.128 -1928.581 328.765</Waypoint>
  <Waypoint>4031.147 -1931.703 328.7092</Waypoint>
  <Waypoint>4094.949 -1932.899 327.687</Waypoint>
  <Waypoint>4158.943 -1928.75 324.2299</Waypoint>
  <Waypoint>4223.032 -1925.186 320.002</Waypoint>
  <Waypoint>4286.672 -1927.454 309.3586</Waypoint>
  <Waypoint>4347.875 -1941.667 298.4443</Waypoint>
  <Waypoint>4405.066 -1969.04 289.2088</Waypoint>
  <Waypoint>4453.29 -2010.358 281.3394</Waypoint>
  <Waypoint>4497.194 -2056.532 282.381</Waypoint>
  <Waypoint>4535.18 -2108.874 289.4678</Waypoint>
  <Waypoint>4574.136 -2157.909 298.644</Waypoint>
  <Waypoint>4594.442 -2216.483 306.3435</Waypoint>
  <Waypoint>4582.076 -2279.353 313.3546</Waypoint>
  <Waypoint>4549.532 -2331.331 325.2777</Waypoint>
  <Waypoint>4489.914 -2351.373 332.7608</Waypoint>
  <Waypoint>4428.654 -2336.316 335.0804</Waypoint>
  <Waypoint>4368.998 -2310.863 330.4364</Waypoint>
  <Waypoint>4310.318 -2285.087 324.3216</Waypoint>
  <Waypoint>4251.347 -2259.184 318.1765</Waypoint>
  <Waypoint>4192.754 -2233.446 312.0708</Waypoint>
  <Waypoint>4130.917 -2219.81 316.6097</Waypoint>
  <Waypoint>4067 -2220.302 322.0406</Waypoint>
  <Waypoint>4004.374 -2231.917 318.7007</Waypoint>
  <Waypoint>3941.609 -2243.564 311.5006</Waypoint>
  <Waypoint>3878.165 -2250.29 301.5493</Waypoint>
  <Waypoint>3816.357 -2254.814 287.4694</Waypoint>
  <Waypoint>3753.401 -2259.422 273.1279</Waypoint>
  <Waypoint>3690.773 -2263.031 260.8524</Waypoint>
  <Waypoint>3626.859 -2259.667 266.8593</Waypoint>
  <Waypoint>3563.093 -2257.202 273.1728</Waypoint>
  <Waypoint>3499.801 -2256.328 278.6544</Waypoint>
  <Waypoint>3436.765 -2256.192 278.0816</Waypoint>
  <Waypoint>3372.132 -2255.838 277.3484</Waypoint>
  <Waypoint>3308.105 -2255.487 276.6221</Waypoint>
  <Waypoint>3244.271 -2255.137 275.898</Waypoint>
  <Waypoint>3179.574 -2254.783 275.1641</Waypoint>
  <Waypoint>3115.464 -2253.27 271.6869</Waypoint>
  <Waypoint>3059.007 -2241.255 243.2404</Waypoint>
  <Waypoint>3003.413 -2229.424 213.897</Waypoint>
  <Waypoint>2948.072 -2218.371 182.9834</Waypoint>
  <Waypoint>2892.542 -2207.422 152.9219</Waypoint>
  <Waypoint>2833.29 -2193.846 134.288</Waypoint>
  <Waypoint>2772.156 -2180.279 120.9259</Waypoint>
  <Waypoint>2710.461 -2166.642 107.2968</Waypoint>
  <Waypoint>2649.723 -2161.084 102.0302</Waypoint>
  <Waypoint>2588.22 -2158.573 98.26547</Waypoint>
  <Waypoint>2530.848 -2183.101 94.31366</Waypoint>
  <Waypoint>2515.758 -2238.589 90.68924</Waypoint>
  <Waypoint>2521.202 -2298.973 86.92451</Waypoint>
  <Waypoint>2566.825 -2343.609 88.14234</Waypoint>
  <Waypoint>2617.831 -2378.429 104.9294</Waypoint>
  <Waypoint>2673.828 -2404.102 122.0415</Waypoint>
  <Waypoint>2736.672 -2403.263 135.2838</Waypoint>
  <Waypoint>2799.572 -2398.836 147.9537</Waypoint>
  <Waypoint>2862.397 -2397.514 162.3952</Waypoint>
  <Waypoint>2924.808 -2396.342 176.8049</Waypoint>
  <Waypoint>2987.14 -2389.657 190.7065</Waypoint>
  <Waypoint>3045.883 -2370.03 205.1097</Waypoint>
  <Waypoint>3086.173 -2324.127 219.9485</Waypoint>
  <Waypoint>3106.798 -2264.188 231.8415</Waypoint>
  <Waypoint>3131.886 -2206.126 238.9077</Waypoint>
  <Waypoint>3168.532 -2155.125 245.4712</Waypoint>
  <Waypoint>3220.306 -2116.106 254.2284</Waypoint>
  <Waypoint>3273.2 -2079.353 257.5925</Waypoint>
  <Waypoint>3326.727 -2044.529 254.5602</Waypoint>
  <Waypoint>3381.269 -2010.93 248.8046</Waypoint>
  <Waypoint>3436.257 -1977.833 243.4235</Waypoint>
  <Waypoint>3493.042 -1948.737 241.946</Waypoint>
  <Waypoint>3553.876 -1929.111 246.5319</Waypoint>
  <Waypoint>3617.204 -1917.651 252.2505</Waypoint>
  <Waypoint>3680.475 -1911.574 258.4701</Waypoint>
  <Waypoint>3743.021 -1925.642 258.7129</Waypoint>
  <Waypoint>3803.965 -1944.861 255.8293</Waypoint>
  <Waypoint>3819.177 -1949.633 255.1053</Waypoint>
  <Waypoint>3830.054 -1954.084 254.3403</Waypoint>
  <Waypoint>3848.836 -1970.044 252.7126</Waypoint>
  <Waypoint>3843.208 -2029.693 252.7451</Waypoint>
  <Waypoint>3827.36 -2092.22 250.3271</Waypoint>
  <Waypoint>3815.942 -2155.422 247.3108</Waypoint>
  <Waypoint>3820.779 -2218.181 251.444</Waypoint>
  <Waypoint>3849.379 -2273.839 265.1371</Waypoint>
  <Waypoint>3871.336 -2332.31 279.2038</Waypoint>
  <Waypoint>3894.474 -2390.918 292.2627</Waypoint>
  <Waypoint>3937.566 -2433.406 304.0708</Waypoint>
  <Waypoint>4000.713 -2442.064 316.9162</Waypoint>
  <Waypoint>4059.555 -2423.282 326.3433</Waypoint>
  <Waypoint>4115.754 -2389.646 321.3223</Waypoint>
  <Waypoint>4170.603 -2355.858 316.8741</Waypoint>
  <Waypoint>4224.882 -2322.421 312.4721</Waypoint>
  <Waypoint>4279.27 -2288.917 308.0613</Waypoint>
  <Waypoint>4332.738 -2254.699 299.9037</Waypoint>
  <Waypoint>4381.826 -2216.39 288.3028</Waypoint>
  <Waypoint>4433.937 -2178.881 286.5518</Waypoint>
  <Waypoint>4483.611 -2159.422 285.893</Waypoint>
  <Waypoint>4548.346 -2185.057 281.5014</Waypoint>
  <Waypoint>4581.319 -2239.062 278.2036</Waypoint>
  <Waypoint>4609.46 -2296.761 287.2449</Waypoint>
  <Waypoint>4629.183 -2356.66 298.1743</Waypoint>
  <Waypoint>4639.168 -2416.417 319.8321</Waypoint>
  <Waypoint>4644.134 -2477.036 340.1149</Waypoint>
  <Waypoint>4621.421 -2531.919 358.1162</Waypoint>
  <Waypoint>4562.28 -2556.07 360.5076</Waypoint>
  <Waypoint>4500.324 -2561.481 349.8978</Waypoint>
  <Waypoint>4438.097 -2550.734 331.5195</Waypoint>
  <Waypoint>4376.563 -2534.653 327.4221</Waypoint>
  <Waypoint>4313.952 -2517.685 325.6669</Waypoint>
  <Waypoint>4252.203 -2500.949 323.9358</Waypoint>
  <Waypoint>4189.579 -2492.299 318.3223</Waypoint>
  <Waypoint>4125.87 -2501.959 319.7722</Waypoint>
  <Waypoint>4062.198 -2511.081 319.9</Waypoint>
  <Waypoint>3998.812 -2516.262 312.8692</Waypoint>
  <Waypoint>3938.4 -2519.481 299.2699</Waypoint>
  <Waypoint>3873.957 -2523.943 283.5227</Waypoint>
  <Waypoint>3811.494 -2528.268 268.2594</Waypoint>
  <Waypoint>3760.075 -2531.829 255.695</Waypoint>
  <Waypoint>3705.315 -2535.62 242.3141</Waypoint>
  <Waypoint>3642.492 -2538.038 231.4705</Waypoint>
  <Waypoint>3578.621 -2530.381 227.7755</Waypoint>
  <Waypoint>3515.465 -2527.643 219.2976</Waypoint>
  <Waypoint>3454.473 -2534.959 202.1433</Waypoint>
  <Waypoint>3396.486 -2547.275 177.5104</Waypoint>
  <Waypoint>3339.352 -2560.898 151.2983</Waypoint>
  <Waypoint>3277.99 -2564.036 139.6115</Waypoint>
  <Waypoint>3213.955 -2558.762 142.4377</Waypoint>
  <Waypoint>3155.4 -2533.409 145.9012</Waypoint>
  <Waypoint>3100.344 -2501.325 138.4541</Waypoint>
  <Waypoint>3058.449 -2476.683 132.0121</Waypoint>
  <Waypoint>3003.545 -2444.388 123.5697</Waypoint>
  <Waypoint>2948.313 -2411.902 115.0769</Waypoint>
  <Waypoint>2894.663 -2380.345 106.8273</Waypoint>
  <Waypoint>2844.5 -2351.131 99.75993</Waypoint>
  <Waypoint>2781.159 -2344.472 97.42815</Waypoint>
  <Waypoint>2717.923 -2351.884 90.05051</Waypoint>
  <Waypoint>2654.538 -2359.219 82.44151</Waypoint>
  <Waypoint>2594.043 -2380.482 78.44592</Waypoint>
  <Waypoint>2548.817 -2423.186 75.16248</Waypoint>
  <Waypoint>2562.136 -2482.622 78.32844</Waypoint>
  <Waypoint>2612.445 -2519.897 90.33778</Waypoint>
  <Waypoint>2668.795 -2542.998 109.9036</Waypoint>
  <Waypoint>2725.209 -2564.789 131.2109</Waypoint>
  <Waypoint>2781.923 -2587.089 152.3731</Waypoint>
  <Waypoint>2837.514 -2608.948 173.1164</Waypoint>
  <Waypoint>2894.929 -2631.524 194.5403</Waypoint>
  <Waypoint>2956.131 -2649.551 200.453</Waypoint>
  <Waypoint>3018.259 -2666.39 203.6013</Waypoint>
  <Waypoint>3080.232 -2683.188 206.7417</Waypoint>
  <Waypoint>3141.008 -2697.724 219.0927</Waypoint>
  <Waypoint>3200.754 -2714.281 238.3091</Waypoint>
  <Waypoint>3257.269 -2738.756 254.8049</Waypoint>
  <Waypoint>3314.675 -2766.646 265.6659</Waypoint>
  <Waypoint>3371.888 -2793.953 273.45</Waypoint>
  <Waypoint>3429.501 -2821.451 281.2885</Waypoint>
  <Waypoint>3486.047 -2850.072 288.9987</Waypoint>
  <Waypoint>3536.528 -2889.205 298.5564</Waypoint>
  <Waypoint>3590.941 -2921.819 308.7668</Waypoint>
  <Waypoint>3648.507 -2947.85 317.611</Waypoint>
  <Waypoint>3709.34 -2938.539 323.0096</Waypoint>
  <Waypoint>3750.294 -2890.759 310.3362</Waypoint>
  <Waypoint>3787.643 -2841.786 293.3643</Waypoint>
  <Waypoint>3840.178 -2804.789 292.1589</Waypoint>
  <Waypoint>3898.176 -2779.604 299.316</Waypoint>
  <Waypoint>3960.829 -2778.257 312.3725</Waypoint>
  <Waypoint>4023.844 -2778.69 325.856</Waypoint>
  <Waypoint>4086.75 -2778.228 339.0974</Waypoint>
  <Waypoint>4149.29 -2777.942 352.0383</Waypoint>
  <Waypoint>4212.619 -2778.552 363.6202</Waypoint>
  <Waypoint>4275.555 -2779.342 374.8318</Waypoint>
  <Waypoint>4329.199 -2805.252 383.7129</Waypoint>
  <Waypoint>4357.597 -2862.568 392.6639</Waypoint>
  <Waypoint>4379.603 -2922.506 400.6735</Waypoint>
  <Waypoint>4390.876 -2984.687 405.4165</Waypoint>
  <Waypoint>4368.432 -3043.83 404.0441</Waypoint>
  <Waypoint>4320.33 -3085.524 398.7809</Waypoint>
  <Waypoint>4261.677 -3112.851 390.7261</Waypoint>
  <Waypoint>4198.767 -3118.913 379.9209</Waypoint>
  <Waypoint>4136.401 -3108.926 369.3955</Waypoint>
  <Waypoint>4078.292 -3082.846 362.9111</Waypoint>
  <Waypoint>4026.251 -3045.869 361.0625</Waypoint>
  <Waypoint>3972.579 -3010.796 359.4411</Waypoint>
  <Waypoint>3912.712 -2987.817 357.7814</Waypoint>
  <Waypoint>3849.474 -2979.356 354.1634</Waypoint>
  <Waypoint>3785.314 -2977.744 349.056</Waypoint>
  <Waypoint>3720.932 -2978.567 346.5953</Waypoint>
  <Waypoint>3656.872 -2982.498 349.6818</Waypoint>
  <Waypoint>3593.154 -2986.407 352.5665</Waypoint>
  <Waypoint>3530.169 -2995.032 347.3654</Waypoint>
  <Waypoint>3474.481 -3010.517 319.8863</Waypoint>
  <Waypoint>3414.331 -3026.025 304.6921</Waypoint>
  <Waypoint>3351.508 -3033.806 290.1004</Waypoint>
  <Waypoint>3289.166 -3032.602 275.2292</Waypoint>
  <Waypoint>3228.784 -3020.404 258.363</Waypoint>
  <Waypoint>3170.516 -3008.004 234.4391</Waypoint>
  <Waypoint>3112.722 -2995.705 209.3576</Waypoint>
  <Waypoint>3054.59 -2983.894 186.2887</Waypoint>
  <Waypoint>2991.781 -2974.794 175.0632</Waypoint>
  <Waypoint>2927.583 -2967.336 172.9866</Waypoint>
  <Waypoint>2863.994 -2959.065 172.661</Waypoint>
  <Waypoint>2800.784 -2950.503 176.6723</Waypoint>
  <Waypoint>2738.584 -2935.123 170.0191</Waypoint>
  <Waypoint>2678.95 -2918.71 163.9546</Waypoint>
  <Waypoint>2644.738 -2909.293 160.4754</Waypoint>
  <Waypoint>2586.682 -2892.241 153.3335</Waypoint>
  <Waypoint>2524.685 -2895.662 151.3648</Waypoint>
  <Waypoint>2494.196 -2947.731 166.9811</Waypoint>
  <Waypoint>2485.066 -3004.894 194.4145</Waypoint>
  <Waypoint>2500.018 -3060.21 222.6662</Waypoint>
  <Waypoint>2539.611 -3103.598 240.5783</Waypoint>
  <Waypoint>2603.556 -3118.671 240.9481</Waypoint>
  <Waypoint>2666.807 -3128.743 238.7932</Waypoint>
  <Waypoint>2727.466 -3147.636 243.3791</Waypoint>
  <Waypoint>2784.569 -3169.553 255.9087</Waypoint>
  <Waypoint>2843.139 -3192.054 268.8453</Waypoint>
  <Waypoint>2901.826 -3214.6 281.8076</Waypoint>
  <Waypoint>2961.038 -3237.348 294.886</Waypoint>
  <Waypoint>3018.616 -3259.468 307.6035</Waypoint>
  <Waypoint>3077.653 -3282.148 320.6432</Waypoint>
  <Waypoint>3136.311 -3304.683 333.5991</Waypoint>
  <Waypoint>3191.551 -3332.972 342.6561</Waypoint>
  <Waypoint>3241.337 -3374.292 343.2773</Waypoint>
  <Waypoint>3291.295 -3415.753 343.9006</Waypoint>
  <Waypoint>3340.541 -3456.624 344.515</Waypoint>
  <Waypoint>3390.057 -3497.719 345.1328</Waypoint>
  <Waypoint>3439.573 -3538.814 345.7506</Waypoint>
  <Waypoint>3489.335 -3580.113 346.3715</Waypoint>
  <Waypoint>3517.358 -3629.564 331.4462</Waypoint>
  <Waypoint>3535.087 -3686.329 309.9054</Waypoint>
  <Waypoint>3560.801 -3744.497 294.2482</Waypoint>
  <Waypoint>3587.061 -3799.845 276.2852</Waypoint>
  <Waypoint>3629.031 -3843.308 257.8078</Waypoint>
  <Waypoint>3690.612 -3850.445 248.4936</Waypoint>
  <Waypoint>3754.057 -3839.368 245.0271</Waypoint>
  <Waypoint>3816.015 -3821.388 250.7955</Waypoint>
  <Waypoint>3874.386 -3801.971 268.9979</Waypoint>
  <Waypoint>3928.697 -3783.234 289.9656</Waypoint>
  <Waypoint>3977.084 -3766.541 308.6462</Waypoint>
  <Waypoint>4034.428 -3746.758 330.7849</Waypoint>
  <Waypoint>4091.658 -3727.014 352.8798</Waypoint>
  <Waypoint>4148.574 -3702.413 354.2415</Waypoint>
  <Waypoint>4203.754 -3672.875 344.4768</Waypoint>
  <Waypoint>4260.63 -3641.141 333.9281</Waypoint>
  <Waypoint>4315.553 -3610.498 323.7418</Waypoint>
  <Waypoint>4375.09 -3586.718 322.2462</Waypoint>
  <Waypoint>4435.802 -3591.479 317.6244</Waypoint>
  <Waypoint>4489.081 -3624.284 326.2086</Waypoint>
  <Waypoint>4546.017 -3639.394 343.6516</Waypoint>
  <Waypoint>4606.407 -3618.296 354.5773</Waypoint>
  <Waypoint>4631.395 -3561.376 362.2182</Waypoint>
  <Waypoint>4614.108 -3501.196 367.3626</Waypoint>
  <Waypoint>4568.445 -3458.984 366.1086</Waypoint>
  <Waypoint>4506.004 -3469.569 364.4781</Waypoint>
  <Waypoint>4450.386 -3502.148 363.0003</Waypoint>
  <Waypoint>4394.864 -3534.345 360.2176</Waypoint>
  <Waypoint>4339.261 -3565.943 356.4741</Waypoint>
  <Waypoint>4284.572 -3597.021 352.7922</Waypoint>
  <Waypoint>4224.366 -3611.491 345.0723</Waypoint>
  <Waypoint>4163.955 -3591.008 343.752</Waypoint>
  <Waypoint>4110.223 -3556.63 347.2522</Waypoint>
  <Waypoint>4061.756 -3514.075 352.7816</Waypoint>
  <Waypoint>4013.683 -3471.892 358.2647</Waypoint>
  <Waypoint>3965.313 -3429.61 362.8873</Waypoint>
  <Waypoint>3909.395 -3399.785 366.8527</Waypoint>
  <Waypoint>3849.305 -3382.917 381.0124</Waypoint>
  <Waypoint>3788.305 -3367.752 394.22</Waypoint>
  <Waypoint>3725.584 -3356.967 393.472</Waypoint>
  <Waypoint>3667.623 -3331.284 380.7543</Waypoint>
  <Waypoint>3614.052 -3308.553 354.3577</Waypoint>
  <Waypoint>3559.971 -3286.043 328.8014</Waypoint>
  <Waypoint>3501.034 -3274.172 308.8207</Waypoint>
  <Waypoint>3440.575 -3293.745 310.1345</Waypoint>
  <Waypoint>3380.882 -3314.962 322.1544</Waypoint>
  <Waypoint>3334.749 -3349.428 349.2926</Waypoint>
  <Waypoint>3288.067 -3381.56 380.1291</Waypoint>
  <Waypoint>3241.72 -3412.949 412.5779</Waypoint>
  <Waypoint>3195.853 -3444.014 444.6904</Waypoint>
  <Waypoint>3149.299 -3475.543 477.2832</Waypoint>
  <Waypoint>3108.028 -3503.495 506.1781</Waypoint>
  <Waypoint>3060.046 -3537.106 526.192</Waypoint>
  <Waypoint>3018.469 -3585.907 528.256</Waypoint>
  <Waypoint>3000.319 -3645.809 535.0633</Waypoint>
  <Waypoint>2991.019 -3702.918 564.4742</Waypoint>
  <Waypoint>2982.105 -3758.624 595.2326</Waypoint>
  <Waypoint>2973.133 -3814.689 626.1896</Waypoint>
  <Waypoint>2971.354 -3871.976 655.107</Waypoint>
  <Waypoint>2981.502 -3929.211 675.0071</Waypoint>
  <Waypoint>3005.443 -3990.388 670.0233</Waypoint>
  <Waypoint>3043.637 -4033.419 639.7291</Waypoint>
  <Waypoint>3058.332 -4082.954 602.0161</Waypoint>
  <Waypoint>3045.9 -4130.716 562.177</Waypoint>
  <Waypoint>3023.22 -4176.024 522.0595</Waypoint>
  <Waypoint>3015.661 -4227.491 485.5375</Waypoint>
  <Waypoint>3035.391 -4278.015 452.4897</Waypoint>
  <Waypoint>3089.381 -4297.939 432.3334</Waypoint>
  <Waypoint>3153.349 -4291.646 435.6864</Waypoint>
  <Waypoint>3216.755 -4284.751 440.1465</Waypoint>
  <Waypoint>3265.71 -4254.951 443.0146</Waypoint>
  <Waypoint>3290.588 -4196.479 449.7921</Waypoint>
  <Waypoint>3315.684 -4137.482 456.644</Waypoint>
  <Waypoint>3319.886 -4081.784 479.9952</Waypoint>
  <Waypoint>3311.807 -4028.379 514.5582</Waypoint>
  <Waypoint>3303.268 -3975.122 549.8138</Waypoint>
  <Waypoint>3292.289 -3922.869 586.2796</Waypoint>
  <Waypoint>3276.233 -3873.407 623.7507</Waypoint>
  <Waypoint>3261.405 -3835.336 651.9361</Waypoint>
  <Waypoint>3232.754 -3791.487 683.8431</Waypoint>
  <Waypoint>3174.433 -3774.65 704.8962</Waypoint>
  <Waypoint>3118.159 -3780.183 729.6296</Waypoint>
  <Waypoint>3070.898 -3815.246 753.901</Waypoint>
  <Waypoint>3054.718 -3872.142 777.4807</Waypoint>
  <Waypoint>3081.633 -3926.176 791.6314</Waypoint>
  <Waypoint>3137.41 -3905.916 797.9183</Waypoint>
  <Waypoint>3161.85 -3855.588 790.7248</Waypoint>
  <Waypoint>3173.14 -3799.379 764.6559</Waypoint>
  <Waypoint>3195.721 -3762.456 718.1181</Waypoint>
  <Waypoint>3222.68 -3729.674 669.4139</Waypoint>
  <Waypoint>3251.816 -3698.521 621.0649</Waypoint>
  <Waypoint>3286.207 -3676.32 572.03</Waypoint>
  <Waypoint>3321.494 -3666.654 519.0385</Waypoint>
  <Waypoint>3363.181 -3663.309 470.1848</Waypoint>
  <Waypoint>3406.407 -3667.371 422.886</Waypoint>
  <Waypoint>3449.124 -3686.812 378.7066</Waypoint>
  <Waypoint>3487.252 -3726.466 347.4831</Waypoint>
  <Waypoint>3517.589 -3779.832 328.6931</Waypoint>
  <Waypoint>3545.208 -3835.332 314.2673</Waypoint>
  <Waypoint>3575.978 -3890.587 301.3079</Waypoint>
  <Waypoint>3622.969 -3931.166 289.9696</Waypoint>
  <Waypoint>3683.941 -3948.8 281.3253</Waypoint>
  <Waypoint>3746.759 -3964.513 273.6041</Waypoint>
  <Waypoint>3808.409 -3979.935 266.0265</Waypoint>
  <Waypoint>3869.198 -3995.141 258.5547</Waypoint>
  <Waypoint>3931.709 -4010.778 250.8713</Waypoint>
  <Waypoint>3994.044 -4024.842 244.107</Waypoint>
  <Waypoint>4058.063 -4023.932 251.9272</Waypoint>
  <Waypoint>4121.284 -4017.118 263.3029</Waypoint>
  <Waypoint>4184.005 -4010.934 275.466</Waypoint>
  <Waypoint>4246.198 -4003.897 288.6429</Waypoint>
  <Waypoint>4305.11 -3982.02 299.4231</Waypoint>
  <Waypoint>4350.898 -3939.561 307.1077</Waypoint>
  <Waypoint>4388.793 -3886.537 315.1376</Waypoint>
  <Waypoint>4423.593 -3832.753 319.7162</Waypoint>
  <Waypoint>4435.866 -3770.336 326.9824</Waypoint>
  <Waypoint>4411.948 -3711.558 330.6788</Waypoint>
  <Waypoint>4379.488 -3656.683 323.0211</Waypoint>
  <Waypoint>4348.484 -3603.61 320.8097</Waypoint>
  <Waypoint>4344.451 -3596.764 320.6155</Waypoint>
  <Waypoint>4348.467 -3585.944 323.0264</Waypoint>
  <Waypoint>4398.136 -3547.777 335.575</Waypoint>
  <Waypoint>4454.271 -3516.345 331.9284</Waypoint>
  <Waypoint>4515.311 -3526.685 329.1656</Waypoint>
  <Waypoint>4571.023 -3555.817 332.1652</Waypoint>
  <Waypoint>4618.043 -3596.689 347.2296</Waypoint>
  <Waypoint>4659.961 -3638.482 371.6499</Waypoint>
  <Waypoint>4687.759 -3691.335 390.8182</Waypoint>
  <Waypoint>4689.405 -3755.792 392.0126</Waypoint>
  <Waypoint>4687.77 -3818.329 378.8277</Waypoint>
  <Waypoint>4666.771 -3872.548 361.8633</Waypoint>
  <Waypoint>4610.398 -3889.143 339.7352</Waypoint>
  <Waypoint>4557.832 -3862.702 322.8577</Waypoint>
  <Waypoint>4512.083 -3821.682 325.9973</Waypoint>
  <Waypoint>4454.404 -3792.767 331.5026</Waypoint>
  <Waypoint>4398.638 -3762 333.2686</Waypoint>
  <Waypoint>4345.775 -3726.416 335.9774</Waypoint>
  <Waypoint>4323.898 -3707.237 337.6804</Waypoint>
  <Waypoint>4294.626 -3698.855 339.0337</Waypoint>
  <Waypoint>4250.664 -3742.914 338.5279</Waypoint>
  <Waypoint>4228.989 -3801.967 333.7827</Waypoint>
  <Waypoint>4269.82 -3847.702 338.4932</Waypoint>
  <Waypoint>4332.471 -3856.153 345.2081</Waypoint>
  <Waypoint>4395.535 -3847.573 354.493</Waypoint>
  <Waypoint>4458.398 -3839.518 362.7705</Waypoint>
  <Waypoint>4522.709 -3835.812 362.7477</Waypoint>
  <Waypoint>4585.059 -3834.947 372.6377</Waypoint>
  <Waypoint>4646.641 -3836.266 392.954</Waypoint>
  <Waypoint>4708.048 -3836.865 412.1805</Waypoint>
  <Waypoint>4769.577 -3837.449 431.3453</Waypoint>
  <Waypoint>4826.064 -3853.13 448.7329</Waypoint>
  <Waypoint>4846.644 -3908.224 473.8855</Waypoint>
  <Waypoint>4828.342 -3963.274 487.6371</Waypoint>
  <Waypoint>4776.708 -3988.364 473.218</Waypoint>
  <Waypoint>4733.352 -3998.572 428.7617</Waypoint>
  <Waypoint>4705.371 -4003.403 371.6102</Waypoint>
  <Waypoint>4685.222 -4014.642 311.7847</Waypoint>
  <Waypoint>4654.22 -4036.843 262.5348</Waypoint>
  <Waypoint>4599.504 -4066.45 240.5156</Waypoint>
  <Waypoint>4539.106 -4084.47 232.4015</Waypoint>
  <Waypoint>4475.223 -4090.811 237.4049</Waypoint>
  <Waypoint>4412.407 -4091.193 247.6603</Waypoint>
  <Waypoint>4349.502 -4092.079 260.5742</Waypoint>
  <Waypoint>4286.034 -4092.973 273.6036</Waypoint>
  <Waypoint>4223.223 -4093.858 286.4983</Waypoint>
  <Waypoint>4159.795 -4095.597 293.6523</Waypoint>
  <Waypoint>4095.945 -4100.073 288.7419</Waypoint>
  <Waypoint>4068.804 -4106.505 284.8274</Waypoint>
  <Waypoint>4062.744 -4108.229 284.337</Waypoint>
  <Waypoint>4009.656 -4106.104 298.214</Waypoint>
  <Waypoint>3945.928 -4100.145 303.989</Waypoint>
  <Waypoint>3882.08 -4099.347 312.4256</Waypoint>
  <Waypoint>3821.854 -4117.9 327.1046</Waypoint>
  <Waypoint>3771.584 -4155.472 316.7569</Waypoint>
  <Waypoint>3731.497 -4200.063 295.4578</Waypoint>
  <Waypoint>3722.751 -4211.753 291.1682</Waypoint>
  <Waypoint>3704.108 -4237.403 281.6103</Waypoint>
  <Waypoint>3648.857 -4268.041 273.8763</Waypoint>
  <Waypoint>3588.347 -4290.816 277.6767</Waypoint>
  <Waypoint>3529.815 -4309.993 294.1529</Waypoint>
  <Waypoint>3474.874 -4340.516 302.4339</Waypoint>
  <Waypoint>3428.073 -4383.93 309.0393</Waypoint>
  <Waypoint>3389.925 -4435.522 315.5707</Waypoint>
  <Waypoint>3353.005 -4487.613 322.5068</Waypoint>
  <Waypoint>3314.451 -4538.791 326.7406</Waypoint>
  <Waypoint>3288.316 -4593.192 337.7058</Waypoint>
  <Waypoint>3298.303 -4656.331 340.8867</Waypoint>
  <Waypoint>3335.972 -4709.252 336.2769</Waypoint>
  <Waypoint>3388.329 -4732.207 329.8322</Waypoint>
  <Waypoint>3449.015 -4745.392 322.9975</Waypoint>
  <Waypoint>3501.735 -4711.171 316.2238</Waypoint>
  <Waypoint>3534.073 -4656.1 309.3925</Waypoint>
  <Waypoint>3565.339 -4600.357 301.9601</Waypoint>
  <Waypoint>3587.826 -4540.52 293.0182</Waypoint>
  <Waypoint>3609.279 -4479.955 290.2886</Waypoint>
  <Waypoint>3638.07 -4423.138 297.4208</Waypoint>
  <Waypoint>3672.732 -4368.916 305.2912</Waypoint>
  <Waypoint>3727.55 -4339.021 311.5356</Waypoint>
  <Waypoint>3791.323 -4332.741 312.9685</Waypoint>
  <Waypoint>3855.221 -4334.005 315.6604</Waypoint>
  <Waypoint>3919.372 -4334.741 320.4219</Waypoint>
  <Waypoint>3983.144 -4327.854 325.8173</Waypoint>
  <Waypoint>4046.487 -4320.361 331.0614</Waypoint>
  <Waypoint>4110.271 -4312.817 336.3421</Waypoint>
  <Waypoint>4172.59 -4306.444 325.6942</Waypoint>
  <Waypoint>4232.283 -4286.518 313.1438</Waypoint>
  <Waypoint>4289.366 -4264.174 292.0434</Waypoint>
  <Waypoint>4346.611 -4241.561 275.001</Waypoint>
  <Waypoint>4406.125 -4218.997 265.9304</Waypoint>
  <Waypoint>4467.737 -4209.372 253.3613</Waypoint>
  <Waypoint>4530.747 -4216.753 251.0017</Waypoint>
  <Waypoint>4593.632 -4226.942 265.2385</Waypoint>
  <Waypoint>4654.763 -4233.997 283.1499</Waypoint>
  <Waypoint>4715.967 -4240.029 301.4258</Waypoint>
  <Waypoint>4777.354 -4246.081 319.7563</Waypoint>
  <Waypoint>4839.699 -4250.489 327.5382</Waypoint>
  <Waypoint>4900.095 -4269.205 326.2831</Waypoint>
  <Waypoint>4939.709 -4319.61 323.9998</Waypoint>
  <Waypoint>4977.118 -4372.069 324.676</Waypoint>
  <Waypoint>4992.963 -4428.528 330.5097</Waypoint>
  <Waypoint>5052.411 -4426.03 353.1835</Waypoint>
  <Waypoint>5094.318 -4471.979 363.461</Waypoint>
  <Waypoint>5118.114 -4531.803 367.1081</Waypoint>
  <Waypoint>5144.699 -4587.143 369.5742</Waypoint>
  <Waypoint>5172.714 -4644.912 372.1529</Waypoint>
  <Waypoint>5209.11 -4697.597 371.9356</Waypoint>
  <Waypoint>5260.431 -4735.702 371.1698</Waypoint>
  <Waypoint>5319.908 -4751.348 382.2883</Waypoint>
  <Waypoint>5383.62 -4766.914 394.3255</Waypoint>
  <Waypoint>5447.078 -4770.616 405.9789</Waypoint>
  <Waypoint>5496.014 -4791.102 377.3273</Waypoint>
  <Waypoint>5506.282 -4844.565 346.4026</Waypoint>
  <Waypoint>5471.678 -4897.98 338.0155</Waypoint>
  <Waypoint>5423.014 -4940.544 339.3702</Waypoint>
  <Waypoint>5374.3 -4982.811 340.7776</Waypoint>
  <Waypoint>5322.474 -5018.458 341.3476</Waypoint>
  <Waypoint>5267.002 -5024.544 341.3805</Waypoint>
  <Waypoint>5202.937 -5030.597 341.6052</Waypoint>
  <Waypoint>5138.84 -5036.652 341.83</Waypoint>
  <Waypoint>5077.857 -5042.413 342.0439</Waypoint>
  <Waypoint>5017.542 -5048.111 342.2555</Waypoint>
  <Waypoint>4957.128 -5035.292 351.3243</Waypoint>
  <Waypoint>4904.703 -5009.521 378.3043</Waypoint>
  <Waypoint>4865.606 -4985.402 359.7505</Waypoint>
  <Waypoint>4854.714 -4926.802 360.1839</Waypoint>
  <Waypoint>4903.98 -4900.906 383.8663</Waypoint>
  <Waypoint>4963.452 -4885.598 399.2438</Waypoint>
  <Waypoint>5026.52 -4868.714 403.9633</Waypoint>
  <Waypoint>5089.727 -4857.679 402.0625</Waypoint>
  <Waypoint>5153.122 -4846.619 400.0964</Waypoint>
  <Waypoint>5212.15 -4823.371 399.1013</Waypoint>
  <Waypoint>5261.311 -4782.905 394.9801</Waypoint>
  <Waypoint>5299.344 -4731.65 399.2303</Waypoint>
  <Waypoint>5322.403 -4671.616 407.9031</Waypoint>
  <Waypoint>5311.228 -4611.792 417.0844</Waypoint>
  <Waypoint>5257.819 -4578.957 414.3362</Waypoint>
  <Waypoint>5197.559 -4586.738 395.8565</Waypoint>
  <Waypoint>5161.349 -4634.785 375.7889</Waypoint>
  <Waypoint>5159.612 -4698.209 370.8222</Waypoint>
  <Waypoint>5166.65 -4760.942 380.23</Waypoint>
  <Waypoint>5170.425 -4824.187 382.143</Waypoint>
  <Waypoint>5151.075 -4870.824 373.8008</Waypoint>
  <Waypoint>5130.891 -4870.296 365.8286</Waypoint>
  <Waypoint>5103.947 -4850.257 353.7893</Waypoint>
  <Waypoint>5059.026 -4804.824 350.3395</Waypoint>
  <Waypoint>5017.519 -4756.206 344.3231</Waypoint>
  <Waypoint>4985.332 -4701.833 334.9793</Waypoint>
  <Waypoint>4977.742 -4666.273 327.5806</Waypoint>
  <Waypoint>4958.838 -4624.27 341.4069</Waypoint>
  <Waypoint>4928.02 -4571.99 360.9199</Waypoint>
  <Waypoint>4888.265 -4528.417 379.2584</Waypoint>
  <Waypoint>4837.063 -4531.775 367.1549</Waypoint>
  <Waypoint>4824.324 -4541.176 348.1277</Waypoint>
  <Waypoint>4783.518 -4552.006 306.2989</Waypoint>
  <Waypoint>4722.739 -4559.803 287.5965</Waypoint>
  <Waypoint>4663.828 -4541.922 278.4711</Waypoint>
  <Waypoint>4612.487 -4503.3 275.2732</Waypoint>
  <Waypoint>4565.085 -4460.222 272.3054</Waypoint>
  <Waypoint>4526.212 -4409.428 269.3666</Waypoint>
  <Waypoint>4488.646 -4356.289 266.6676</Waypoint>
  <Waypoint>4464.338 -4299.917 265.3241</Waypoint>
  <Waypoint>4505.658 -4262.129 272.7175</Waypoint>
  <Waypoint>4551.214 -4299.647 277.5843</Waypoint>
  <Waypoint>4565.79 -4324.918 279.963</Waypoint>
  <Waypoint>4578.257 -4340.556 280.9323</Waypoint>
  <Waypoint>4617.586 -4360.979 284.0305</Waypoint>
  <Waypoint>4675.127 -4390.06 283.5042</Waypoint>
  <Waypoint>4732.864 -4417.445 282.4366</Waypoint>
  <Waypoint>4773.122 -4459.522 279.9896</Waypoint>
  <Waypoint>4740.531 -4510.669 280.4261</Waypoint>
  <Waypoint>4677.211 -4523.483 286.7516</Waypoint>
  <Waypoint>4614.132 -4531.875 292.1965</Waypoint>
  <Waypoint>4556.925 -4505.513 293.1909</Waypoint>
  <Waypoint>4506.03 -4466.619 297.4229</Waypoint>
  <Waypoint>4453.527 -4429.688 306.129</Waypoint>
  <Waypoint>4392.545 -4413.06 312.6519</Waypoint>
  <Waypoint>4330.61 -4415.056 328.1485</Waypoint>
  <Waypoint>4267.704 -4419.408 341.7666</Waypoint>
  <Waypoint>4204.789 -4421.599 355.0782</Waypoint>
  <Waypoint>4142.346 -4412.283 352.932</Waypoint>
  <Waypoint>4080.513 -4424.073 343.9359</Waypoint>
  <Waypoint>4023.068 -4451.915 337.4987</Waypoint>
  <Waypoint>3971.363 -4489.361 334.9387</Waypoint>
  <Waypoint>3916.126 -4515.839 316.9193</Waypoint>
  <Waypoint>3861.643 -4522.28 289.7419</Waypoint>
  <Waypoint>3815.156 -4519.628 283.5238</Waypoint>
  <Waypoint>3753.151 -4514.243 267.8903</Waypoint>
  <Waypoint>3693.308 -4522.211 265.8505</Waypoint>
  <Waypoint>3663.36 -4580.191 279.8999</Waypoint>
  <Waypoint>3645.183 -4640.912 289.8246</Waypoint>
  <Waypoint>3626.586 -4702.423 292.1506</Waypoint>
  <Waypoint>3612.657 -4764.965 286.6216</Waypoint>
  <Waypoint>3596.413 -4826.874 289.226</Waypoint>
  <Waypoint>3572.476 -4884.7 302.6111</Waypoint>
  <Waypoint>3516.44 -4905.892 322.1239</Waypoint>
  <Waypoint>3455.993 -4904.998 343.8697</Waypoint>
  <Waypoint>3396.559 -4894.336 364.0789</Waypoint>
  <Waypoint>3338.031 -4881.414 387.4493</Waypoint>
  <Waypoint>3283.243 -4870.064 418.8477</Waypoint>
  <Waypoint>3238.431 -4860.782 444.5288</Waypoint>
  <Waypoint>3172.222 -4850.893 462.8087</Waypoint>
  <Waypoint>3109.801 -4846.469 476.2153</Waypoint>
  <Waypoint>3047.279 -4842.04 489.767</Waypoint>
  <Waypoint>2986.161 -4853.188 492.9281</Waypoint>
  <Waypoint>2943.314 -4896.61 504.2472</Waypoint>
  <Waypoint>2917.391 -4940.102 531.4996</Waypoint>
  <Waypoint>2887.709 -4988.108 562.2087</Waypoint>
  <Waypoint>2860.686 -5041.303 577.5052</Waypoint>
  <Waypoint>2852.643 -5104.239 577.9012</Waypoint>
  <Waypoint>2862.981 -5166.276 589.4762</Waypoint>
  <Waypoint>2876.41 -5229.054 599.9774</Waypoint>
  <Waypoint>2893.226 -5290.729 605.5273</Waypoint>
  <Waypoint>2908.78 -5353.011 605.4702</Waypoint>
  <Waypoint>2906.897 -5416.484 598.3067</Waypoint>
  <Waypoint>2895.198 -5470.083 587.9619</Waypoint>
  <Waypoint>2881.685 -5531.65 575.9948</Waypoint>
  <Waypoint>2867.286 -5582.587 543.5344</Waypoint>
  <Waypoint>2859.863 -5627.641 498.6533</Waypoint>
  <Waypoint>2868.124 -5673.816 454.4894</Waypoint>
  <Waypoint>2870.925 -5721.731 412.5789</Waypoint>
  <Waypoint>2875.227 -5774.562 377.9259</Waypoint>
  <Waypoint>2917.278 -5803.397 346.4462</Waypoint>
  <Waypoint>2974.179 -5782.514 327.2871</Waypoint>
  <Waypoint>3027.154 -5745.899 322.4681</Waypoint>
  <Waypoint>3080.867 -5710.623 314.407</Waypoint>
  <Waypoint>3134.025 -5675.711 306.4292</Waypoint>
  <Waypoint>3187.447 -5640.625 298.4117</Waypoint>
  <Waypoint>3240.843 -5605.557 290.3982</Waypoint>
  <Waypoint>3292.605 -5568 291.5472</Waypoint>
  <Waypoint>3332.904 -5519.891 303.3512</Waypoint>
  <Waypoint>3372.693 -5470.632 316.0043</Waypoint>
  <Waypoint>3408.545 -5420.368 325.6335</Waypoint>
  <Waypoint>3402.638 -5359.331 345.5158</Waypoint>
  <Waypoint>3379.148 -5305.874 367.9463</Waypoint>
  <Waypoint>3354.579 -5248.47 389.7514</Waypoint>
  <Waypoint>3330.64 -5192.534 410.9989</Waypoint>
  <Waypoint>3313.666 -5132.642 419.3503</Waypoint>
  <Waypoint>3303.42 -5068.766 418.506</Waypoint>
  <Waypoint>3293.609 -5005.175 417.5514</Waypoint>
  <Waypoint>3283.755 -4941.3 416.5925</Waypoint>
  <Waypoint>3282.033 -4878.751 406.7746</Waypoint>
  <Waypoint>3325.014 -4836.243 390.5262</Waypoint>
  <Waypoint>3383.02 -4845.958 371.2733</Waypoint>
  <Waypoint>3413.468 -4898.317 353.1131</Waypoint>
  <Waypoint>3431.481 -4959.079 342.7954</Waypoint>
  <Waypoint>3453.229 -5018.731 331.1905</Waypoint>
  <Waypoint>3473.822 -5078.333 318.0283</Waypoint>
  <Waypoint>3471.83 -5141.041 311.7072</Waypoint>
  <Waypoint>3456.841 -5203.544 313.9142</Waypoint>
  <Waypoint>3440.365 -5265.67 316.3272</Waypoint>
  <Waypoint>3425.089 -5328.523 319.4072</Waypoint>
  <Waypoint>3428.5 -5391.812 320.9822</Waypoint>
  <Waypoint>3457.005 -5447.383 309.7786</Waypoint>
  <Waypoint>3512.041 -5465.083 288.0089</Waypoint>
  <Waypoint>3557.827 -5433.916 259.2989</Waypoint>
  <Waypoint>3597.193 -5394.465 225.6882</Waypoint>
  <Waypoint>3634.407 -5352.995 196.2226</Waypoint>
  <Waypoint>3646.263 -5289.968 193.8047</Waypoint>
  <Waypoint>3645.014 -5226.85 202.9138</Waypoint>
  <Waypoint>3642.264 -5163.666 214.4061</Waypoint>
  <Waypoint>3633.821 -5100.462 223.4707</Waypoint>
  <Waypoint>3625.63 -5037.949 232.4807</Waypoint>
  <Waypoint>3623.641 -4974.327 242.4063</Waypoint>
  <Waypoint>3624.376 -4910.252 251.3739</Waypoint>
  <Waypoint>3621.383 -4846.667 259.1335</Waypoint>
  <Waypoint>3619.609 -4782.904 267.0833</Waypoint>
  <Waypoint>3624.812 -4719.585 275.0343</Waypoint>
  <Waypoint>3640.588 -4657.481 280.8366</Waypoint>
  <Waypoint>3660.504 -4595.854 278.7525</Waypoint>
  <Waypoint>3697.805 -4545.294 289.0997</Waypoint>
  <Waypoint>3747.238 -4510.46 307.0858</Waypoint>
  <Waypoint>3808.26 -4503.459 322.0257</Waypoint>
  <Waypoint>3861.755 -4537.255 331.756</Waypoint>
  <Waypoint>3879.185 -4597.501 331.9058</Waypoint>
  <Waypoint>3870.203 -4659.441 321.1939</Waypoint>
  <Waypoint>3855.726 -4716.684 295.6101</Waypoint>
  <Waypoint>3842.394 -4773.785 270.1293</Waypoint>
  <Waypoint>3831.647 -4834.167 249.6219</Waypoint>
  <Waypoint>3824.213 -4894.659 230.2534</Waypoint>
  <Waypoint>3817.273 -4955.301 209.7713</Waypoint>
  <Waypoint>3809.993 -5017.547 195.3113</Waypoint>
  <Waypoint>3803.041 -5080.29 183.526</Waypoint>
  <Waypoint>3803.303 -5108.808 179.4405</Waypoint>
  <Waypoint>3797.836 -5151.157 171.7678</Waypoint>
  <Waypoint>3820.382 -5204.433 155.8513</Waypoint>
  <Waypoint>3877.735 -5208.889 129.28</Waypoint>
  <Waypoint>3933.521 -5185.068 109.7799</Waypoint>
  <Waypoint>3981.886 -5143.843 97.95216</Waypoint>
  <Waypoint>4031.912 -5104.28 92.44828</Waypoint>
  <Waypoint>4013.179 -5055.092 102.4191</Waypoint>
  <Waypoint>3957.634 -5030.172 123.6547</Waypoint>
  <Waypoint>3902.14 -5005.373 144.8811</Waypoint>
  <Waypoint>3846.812 -4980.647 166.0443</Waypoint>
  <Waypoint>3822.514 -4932.709 194.9964</Waypoint>
  <Waypoint>3847.983 -4880.262 218.3562</Waypoint>
  <Waypoint>3891.925 -4835.194 230.1946</Waypoint>
  <Waypoint>3944.612 -4797.959 229.4563</Waypoint>
  <Waypoint>3990.292 -4827.907 210.8235</Waypoint>
  <Waypoint>3998.502 -4885.29 182.2916</Waypoint>
  <Waypoint>4008.38 -4942.969 155.6543</Waypoint>
  <Waypoint>4021.353 -5000.946 131.2778</Waypoint>
  <Waypoint>4029.849 -5060.511 107.6266</Waypoint>
  <Waypoint>4028.154 -5120.632 88.31112</Waypoint>
  <Waypoint>4011.208 -5180.888 73.88246</Waypoint>
  <Waypoint>4011.679 -5241.517 60.71278</Waypoint>
  <Waypoint>4070.722 -5264.386 56.53643</Waypoint>
  <Waypoint>4135.398 -5266.489 55.36295</Waypoint>
  <Waypoint>4199.029 -5271.072 48.99468</Waypoint>
  <Waypoint>4250.366 -5307.681 44.64539</Waypoint>
  <Waypoint>4282.582 -5363.408 40.96092</Waypoint>
  <Waypoint>4332.038 -5400.3 48.70318</Waypoint>
  <Waypoint>4391.785 -5420.204 60.42337</Waypoint>
  <Waypoint>4452.665 -5440.402 69.33451</Waypoint>
  <Waypoint>4514.185 -5457.113 75.79903</Waypoint>
  <Waypoint>4575.891 -5474.018 79.82068</Waypoint>
  <Waypoint>4633.849 -5500.509 86.31158</Waypoint>
  <Waypoint>4688.161 -5533.659 94.08678</Waypoint>
  <Waypoint>4741.807 -5567.709 102.0012</Waypoint>
  <Waypoint>4790.092 -5609.553 107.7603</Waypoint>
  <Waypoint>4816.274 -5667.978 110.1281</Waypoint>
  <Waypoint>4803.371 -5728.875 107.9361</Waypoint>
  <Waypoint>4744.662 -5749.803 114.4875</Waypoint>
  <Waypoint>4681.418 -5749.993 126.5481</Waypoint>
  <Waypoint>4618.146 -5748.864 135.6153</Waypoint>
  <Waypoint>4558.623 -5724.788 143.7349</Waypoint>
  <Waypoint>4519.854 -5676.881 152.1175</Waypoint>
  <Waypoint>4546.198 -5625.625 160.5958</Waypoint>
  <Waypoint>4608.019 -5629.353 167.2907</Waypoint>
  <Waypoint>4663.933 -5657.434 167.8494</Waypoint>
  <Waypoint>4671.024 -5720.031 172.1759</Waypoint>
  <Waypoint>4646.193 -5777.864 185.7523</Waypoint>
  <Waypoint>4595.119 -5797.033 203.6934</Waypoint>
  <Waypoint>4592.39 -5748.509 231.3964</Waypoint>
  <Waypoint>4613.084 -5746.636 242.8955</Waypoint>
  <Waypoint>4612.604 -5727.421 237.7091</Waypoint>
  <Waypoint>4610.248 -5663.891 228.6043</Waypoint>
  <Waypoint>4604.257 -5601.857 215.4971</Waypoint>
  <Waypoint>4574.957 -5549.256 193.4346</Waypoint>
  <Waypoint>4540.441 -5498.641 174.7076</Waypoint>
  <Waypoint>4507.275 -5450.245 156.8822</Waypoint>
  <Waypoint>4472.382 -5399.329 138.1289</Waypoint>
  <Waypoint>4437.869 -5348.968 119.5797</Waypoint>
  <Waypoint>4403.028 -5298.128 100.8543</Waypoint>
  <Waypoint>4368.584 -5247.867 82.34222</Waypoint>
  <Waypoint>4336.128 -5192.666 74.50053</Waypoint>
  <Waypoint>4299.896 -5139.998 66.13394</Waypoint>
  <Waypoint>4264.191 -5087.56 57.50875</Waypoint>
  <Waypoint>4256.742 -5027.605 55.35458</Waypoint>
  <Waypoint>4291.943 -4992.141 60.22579</Waypoint>
  <Waypoint>4326.472 -4968.221 63.30204</Waypoint>
  <Waypoint>4385.814 -4944.876 70.95013</Waypoint>
  <Waypoint>4448.389 -4938.366 85.40833</Waypoint>
  <Waypoint>4509.047 -4954.346 99.52221</Waypoint>
  <Waypoint>4565.433 -4983.97 104.1925</Waypoint>
  <Waypoint>4611.618 -5028.097 100.786</Waypoint>
  <Waypoint>4637.809 -5085.901 94.31493</Waypoint>
  <Waypoint>4658.805 -5146.881 86.32658</Waypoint>
  <Waypoint>4695.147 -5198.757 81.68551</Waypoint>
  <Waypoint>4753.224 -5223.462 80.49287</Waypoint>
  <Waypoint>4801.746 -5188.938 83.03455</Waypoint>
  <Waypoint>4799.752 -5126.543 90.06104</Waypoint>
  <Waypoint>4766.311 -5072.905 99.42006</Waypoint>
  <Waypoint>4730.019 -5020.431 105.1743</Waypoint>
  <Waypoint>4701.067 -4963.267 103.7627</Waypoint>
  <Waypoint>4673.051 -4907.742 102.1884</Waypoint>
  <Waypoint>4644.044 -4850.252 100.5584</Waypoint>
  <Waypoint>4637.618 -4791.143 113.8528</Waypoint>
  <Waypoint>4688.424 -4760.051 124.4381</Waypoint>
  <Waypoint>4736.267 -4795.119 123.3342</Waypoint>
  <Waypoint>4757.646 -4853.588 107.7357</Waypoint>
  <Waypoint>4770.988 -4913.791 89.23642</Waypoint>
  <Waypoint>4763.026 -4975.2 78.60188</Waypoint>
  <Waypoint>4720.91 -5022.857 77.73362</Waypoint>
  <Waypoint>4664.734 -5049.138 82.58514</Waypoint>
  <Waypoint>4620.994 -5005.919 85.20357</Waypoint>
  <Waypoint>4601.324 -4945.606 92.86927</Waypoint>
  <Waypoint>4571.813 -4889.232 101.4296</Waypoint>
  <Waypoint>4516.977 -4857.556 110.2056</Waypoint>
  <Waypoint>4475.625 -4811.711 118.0987</Waypoint>
  <Waypoint>4458.567 -4751.78 129.5784</Waypoint>
  <Waypoint>4451.35 -4689.863 145.352</Waypoint>
  <Waypoint>4443.777 -4628.571 162.1184</Waypoint>
  <Waypoint>4430.552 -4568.839 181.9767</Waypoint>
  <Waypoint>4411.058 -4511.538 203.0842</Waypoint>
  <Waypoint>4382.169 -4458.625 224.3392</Waypoint>
  <Waypoint>4334.052 -4422.546 247.7649</Waypoint>
  <Waypoint>4284.676 -4393.601 275.5786</Waypoint>
  <Waypoint>4229.92 -4376.958 303.6889</Waypoint>
  <Waypoint>4169.38 -4381.177 325.1394</Waypoint>
  <Waypoint>4106.375 -4384.05 336.2094</Waypoint>
  <Waypoint>4043.729 -4391.054 342.5475</Waypoint>
  <Waypoint>3998.194 -4434.407 346.9803</Waypoint>
  <Waypoint>3973.621 -4494.047 349.5766</Waypoint>
  <Waypoint>3952.484 -4553.671 341.8562</Waypoint>
  <Waypoint>3931.365 -4605.657 325.2656</Waypoint>
  <Waypoint>3905.671 -4667.689 303.3197</Waypoint>
  <Waypoint>3882.345 -4724.003 283.3968</Waypoint>
  <Waypoint>3859.008 -4780.346 263.4641</Waypoint>
  <Waypoint>3835.601 -4836.856 243.4718</Waypoint>
  <Waypoint>3812.38 -4892.918 223.6382</Waypoint>
  <Waypoint>3788.983 -4951.084 210.8067</Waypoint>
  <Waypoint>3762.751 -5009.371 212.2146</Waypoint>
  <Waypoint>3735.123 -5067.501 213.6191</Waypoint>
  <Waypoint>3706.805 -5125.305 215.0236</Waypoint>
  <Waypoint>3678.291 -5183.51 216.4378</Waypoint>
  <Waypoint>3650.001 -5241.256 217.8409</Waypoint>
  <Waypoint>3621.922 -5298.572 219.2335</Waypoint>
  <Waypoint>3592.751 -5356.604 221.0204</Waypoint>
  <Waypoint>3557.053 -5409.043 228.2879</Waypoint>
  <Waypoint>3515.832 -5457.724 235.9701</Waypoint>
  <Waypoint>3467.856 -5499.992 243.7884</Waypoint>
  <Waypoint>3414.541 -5535.517 251.7226</Waypoint>
  <Waypoint>3358.318 -5565.955 259.2984</Waypoint>
  <Waypoint>3301.99 -5596.348 267.1005</Waypoint>
  <Waypoint>3246.104 -5626.951 277.6833</Waypoint>
  <Waypoint>3190.338 -5657.609 289.1909</Waypoint>
  <Waypoint>3134.847 -5688.116 300.6417</Waypoint>
  <Waypoint>3079.521 -5718.532 312.0584</Waypoint>
  <Waypoint>3024.223 -5748.933 323.4694</Waypoint>
  <Waypoint>3002.836 -5760.69 327.8827</Waypoint>
  <Waypoint>3002.836 -5760.69 327.8827</Waypoint>
  <Waypoint>3024.223 -5748.933 323.4694</Waypoint>
  <Waypoint>3079.521 -5718.532 312.0584</Waypoint>
  <Waypoint>3134.847 -5688.116 300.6417</Waypoint>
  <Waypoint>3190.338 -5657.609 289.1909</Waypoint>
  <Waypoint>3246.104 -5626.951 277.6833</Waypoint>
  <Waypoint>3301.99 -5596.348 267.1005</Waypoint>
  <Waypoint>3358.318 -5565.955 259.2984</Waypoint>
  <Waypoint>3414.541 -5535.517 251.7226</Waypoint>
  <Waypoint>3467.856 -5499.992 243.7884</Waypoint>
  <Waypoint>3515.832 -5457.724 235.9701</Waypoint>
  <Waypoint>3557.053 -5409.043 228.2879</Waypoint>
  <Waypoint>3592.751 -5356.604 221.0204</Waypoint>
  <Waypoint>3621.922 -5298.572 219.2335</Waypoint>
  <Waypoint>3650.001 -5241.256 217.8409</Waypoint>
  <Waypoint>3678.291 -5183.51 216.4378</Waypoint>
  <Waypoint>3706.805 -5125.305 215.0236</Waypoint>
  <Waypoint>3735.123 -5067.501 213.6191</Waypoint>
  <Waypoint>3762.751 -5009.371 212.2146</Waypoint>
  <Waypoint>3788.983 -4951.084 210.8067</Waypoint>
  <Waypoint>3812.38 -4892.918 223.6382</Waypoint>
  <Waypoint>3835.601 -4836.856 243.4718</Waypoint>
  <Waypoint>3859.008 -4780.346 263.4641</Waypoint>
  <Waypoint>3882.345 -4724.003 283.3968</Waypoint>
  <Waypoint>3905.671 -4667.689 303.3197</Waypoint>
  <Waypoint>3931.365 -4605.657 325.2656</Waypoint>
  <Waypoint>3952.484 -4553.671 341.8562</Waypoint>
  <Waypoint>3973.621 -4494.047 349.5766</Waypoint>
  <Waypoint>3998.194 -4434.407 346.9803</Waypoint>
  <Waypoint>4043.729 -4391.054 342.5475</Waypoint>
  <Waypoint>4106.375 -4384.05 336.2094</Waypoint>
  <Waypoint>4169.38 -4381.177 325.1394</Waypoint>
  <Waypoint>4229.92 -4376.958 303.6889</Waypoint>
  <Waypoint>4284.676 -4393.601 275.5786</Waypoint>
  <Waypoint>4334.052 -4422.546 247.7649</Waypoint>
  <Waypoint>4382.169 -4458.625 224.3392</Waypoint>
  <Waypoint>4411.058 -4511.538 203.0842</Waypoint>
  <Waypoint>4430.552 -4568.839 181.9767</Waypoint>
  <Waypoint>4443.777 -4628.571 162.1184</Waypoint>
  <Waypoint>4451.35 -4689.863 145.352</Waypoint>
  <Waypoint>4458.567 -4751.78 129.5784</Waypoint>
  <Waypoint>4475.625 -4811.711 118.0987</Waypoint>
  <Waypoint>4516.977 -4857.556 110.2056</Waypoint>
  <Waypoint>4571.813 -4889.232 101.4296</Waypoint>
  <Waypoint>4601.324 -4945.606 92.86927</Waypoint>
  <Waypoint>4620.994 -5005.919 85.20357</Waypoint>
  <Waypoint>4664.734 -5049.138 82.58514</Waypoint>
  <Waypoint>4720.91 -5022.857 77.73362</Waypoint>
  <Waypoint>4763.026 -4975.2 78.60188</Waypoint>
  <Waypoint>4770.988 -4913.791 89.23642</Waypoint>
  <Waypoint>4757.646 -4853.588 107.7357</Waypoint>
  <Waypoint>4736.267 -4795.119 123.3342</Waypoint>
  <Waypoint>4688.424 -4760.051 124.4381</Waypoint>
  <Waypoint>4637.618 -4791.143 113.8528</Waypoint>
  <Waypoint>4644.044 -4850.252 100.5584</Waypoint>
  <Waypoint>4673.051 -4907.742 102.1884</Waypoint>
  <Waypoint>4701.067 -4963.267 103.7627</Waypoint>
  <Waypoint>4730.019 -5020.431 105.1743</Waypoint>
  <Waypoint>4766.311 -5072.905 99.42006</Waypoint>
  <Waypoint>4799.752 -5126.543 90.06104</Waypoint>
  <Waypoint>4801.746 -5188.938 83.03455</Waypoint>
  <Waypoint>4753.224 -5223.462 80.49287</Waypoint>
  <Waypoint>4695.147 -5198.757 81.68551</Waypoint>
  <Waypoint>4658.805 -5146.881 86.32658</Waypoint>
  <Waypoint>4637.809 -5085.901 94.31493</Waypoint>
  <Waypoint>4611.618 -5028.097 100.786</Waypoint>
  <Waypoint>4565.433 -4983.97 104.1925</Waypoint>
  <Waypoint>4509.047 -4954.346 99.52221</Waypoint>
  <Waypoint>4448.389 -4938.366 85.40833</Waypoint>
  <Waypoint>4385.814 -4944.876 70.95013</Waypoint>
  <Waypoint>4326.472 -4968.221 63.30204</Waypoint>
  <Waypoint>4291.943 -4992.141 60.22579</Waypoint>
  <Waypoint>4256.742 -5027.605 55.35458</Waypoint>
  <Waypoint>4264.191 -5087.56 57.50875</Waypoint>
  <Waypoint>4299.896 -5139.998 66.13394</Waypoint>
  <Waypoint>4336.128 -5192.666 74.50053</Waypoint>
  <Waypoint>4368.584 -5247.867 82.34222</Waypoint>
  <Waypoint>4403.028 -5298.128 100.8543</Waypoint>
  <Waypoint>4437.869 -5348.968 119.5797</Waypoint>
  <Waypoint>4472.382 -5399.329 138.1289</Waypoint>
  <Waypoint>4507.275 -5450.245 156.8822</Waypoint>
  <Waypoint>4540.441 -5498.641 174.7076</Waypoint>
  <Waypoint>4574.957 -5549.256 193.4346</Waypoint>
  <Waypoint>4604.257 -5601.857 215.4971</Waypoint>
  <Waypoint>4610.248 -5663.891 228.6043</Waypoint>
  <Waypoint>4612.604 -5727.421 237.7091</Waypoint>
  <Waypoint>4613.084 -5746.636 242.8955</Waypoint>
  <Waypoint>4592.39 -5748.509 231.3964</Waypoint>
  <Waypoint>4595.119 -5797.033 203.6934</Waypoint>
  <Waypoint>4646.193 -5777.864 185.7523</Waypoint>
  <Waypoint>4671.024 -5720.031 172.1759</Waypoint>
  <Waypoint>4663.933 -5657.434 167.8494</Waypoint>
  <Waypoint>4608.019 -5629.353 167.2907</Waypoint>
  <Waypoint>4546.198 -5625.625 160.5958</Waypoint>
  <Waypoint>4519.854 -5676.881 152.1175</Waypoint>
  <Waypoint>4558.623 -5724.788 143.7349</Waypoint>
  <Waypoint>4618.146 -5748.864 135.6153</Waypoint>
  <Waypoint>4681.418 -5749.993 126.5481</Waypoint>
  <Waypoint>4744.662 -5749.803 114.4875</Waypoint>
  <Waypoint>4803.371 -5728.875 107.9361</Waypoint>
  <Waypoint>4816.274 -5667.978 110.1281</Waypoint>
  <Waypoint>4790.092 -5609.553 107.7603</Waypoint>
  <Waypoint>4741.807 -5567.709 102.0012</Waypoint>
  <Waypoint>4688.161 -5533.659 94.08678</Waypoint>
  <Waypoint>4633.849 -5500.509 86.31158</Waypoint>
  <Waypoint>4575.891 -5474.018 79.82068</Waypoint>
  <Waypoint>4514.185 -5457.113 75.79903</Waypoint>
  <Waypoint>4452.665 -5440.402 69.33451</Waypoint>
  <Waypoint>4391.785 -5420.204 60.42337</Waypoint>
  <Waypoint>4332.038 -5400.3 48.70318</Waypoint>
  <Waypoint>4282.582 -5363.408 40.96092</Waypoint>
  <Waypoint>4250.366 -5307.681 44.64539</Waypoint>
  <Waypoint>4199.029 -5271.072 48.99468</Waypoint>
  <Waypoint>4135.398 -5266.489 55.36295</Waypoint>
  <Waypoint>4070.722 -5264.386 56.53643</Waypoint>
  <Waypoint>4011.679 -5241.517 60.71278</Waypoint>
  <Waypoint>4011.208 -5180.888 73.88246</Waypoint>
  <Waypoint>4028.154 -5120.632 88.31112</Waypoint>
  <Waypoint>4029.849 -5060.511 107.6266</Waypoint>
  <Waypoint>4021.353 -5000.946 131.2778</Waypoint>
  <Waypoint>4008.38 -4942.969 155.6543</Waypoint>
  <Waypoint>3998.502 -4885.29 182.2916</Waypoint>
  <Waypoint>3990.292 -4827.907 210.8235</Waypoint>
  <Waypoint>3944.612 -4797.959 229.4563</Waypoint>
  <Waypoint>3891.925 -4835.194 230.1946</Waypoint>
  <Waypoint>3847.983 -4880.262 218.3562</Waypoint>
  <Waypoint>3822.514 -4932.709 194.9964</Waypoint>
  <Waypoint>3846.812 -4980.647 166.0443</Waypoint>
  <Waypoint>3902.14 -5005.373 144.8811</Waypoint>
  <Waypoint>3957.634 -5030.172 123.6547</Waypoint>
  <Waypoint>4013.179 -5055.092 102.4191</Waypoint>
  <Waypoint>4031.912 -5104.28 92.44828</Waypoint>
  <Waypoint>3981.886 -5143.843 97.95216</Waypoint>
  <Waypoint>3933.521 -5185.068 109.7799</Waypoint>
  <Waypoint>3877.735 -5208.889 129.28</Waypoint>
  <Waypoint>3820.382 -5204.433 155.8513</Waypoint>
  <Waypoint>3797.836 -5151.157 171.7678</Waypoint>
  <Waypoint>3803.303 -5108.808 179.4405</Waypoint>
  <Waypoint>3803.041 -5080.29 183.526</Waypoint>
  <Waypoint>3809.993 -5017.547 195.3113</Waypoint>
  <Waypoint>3817.273 -4955.301 209.7713</Waypoint>
  <Waypoint>3824.213 -4894.659 230.2534</Waypoint>
  <Waypoint>3831.647 -4834.167 249.6219</Waypoint>
  <Waypoint>3842.394 -4773.785 270.1293</Waypoint>
  <Waypoint>3855.726 -4716.684 295.6101</Waypoint>
  <Waypoint>3870.203 -4659.441 321.1939</Waypoint>
  <Waypoint>3879.185 -4597.501 331.9058</Waypoint>
  <Waypoint>3861.755 -4537.255 331.756</Waypoint>
  <Waypoint>3808.26 -4503.459 322.0257</Waypoint>
  <Waypoint>3747.238 -4510.46 307.0858</Waypoint>
  <Waypoint>3697.805 -4545.294 289.0997</Waypoint>
  <Waypoint>3660.504 -4595.854 278.7525</Waypoint>
  <Waypoint>3640.588 -4657.481 280.8366</Waypoint>
  <Waypoint>3624.812 -4719.585 275.0343</Waypoint>
  <Waypoint>3619.609 -4782.904 267.0833</Waypoint>
  <Waypoint>3621.383 -4846.667 259.1335</Waypoint>
  <Waypoint>3624.376 -4910.252 251.3739</Waypoint>
  <Waypoint>3623.641 -4974.327 242.4063</Waypoint>
  <Waypoint>3625.63 -5037.949 232.4807</Waypoint>
  <Waypoint>3633.821 -5100.462 223.4707</Waypoint>
  <Waypoint>3642.264 -5163.666 214.4061</Waypoint>
  <Waypoint>3645.014 -5226.85 202.9138</Waypoint>
  <Waypoint>3646.263 -5289.968 193.8047</Waypoint>
  <Waypoint>3634.407 -5352.995 196.2226</Waypoint>
  <Waypoint>3597.193 -5394.465 225.6882</Waypoint>
  <Waypoint>3557.827 -5433.916 259.2989</Waypoint>
  <Waypoint>3512.041 -5465.083 288.0089</Waypoint>
  <Waypoint>3457.005 -5447.383 309.7786</Waypoint>
  <Waypoint>3428.5 -5391.812 320.9822</Waypoint>
  <Waypoint>3425.089 -5328.523 319.4072</Waypoint>
  <Waypoint>3440.365 -5265.67 316.3272</Waypoint>
  <Waypoint>3456.841 -5203.544 313.9142</Waypoint>
  <Waypoint>3471.83 -5141.041 311.7072</Waypoint>
  <Waypoint>3473.822 -5078.333 318.0283</Waypoint>
  <Waypoint>3453.229 -5018.731 331.1905</Waypoint>
  <Waypoint>3431.481 -4959.079 342.7954</Waypoint>
  <Waypoint>3413.468 -4898.317 353.1131</Waypoint>
  <Waypoint>3383.02 -4845.958 371.2733</Waypoint>
  <Waypoint>3325.014 -4836.243 390.5262</Waypoint>
  <Waypoint>3282.033 -4878.751 406.7746</Waypoint>
  <Waypoint>3283.755 -4941.3 416.5925</Waypoint>
  <Waypoint>3293.609 -5005.175 417.5514</Waypoint>
  <Waypoint>3303.42 -5068.766 418.506</Waypoint>
  <Waypoint>3313.666 -5132.642 419.3503</Waypoint>
  <Waypoint>3330.64 -5192.534 410.9989</Waypoint>
  <Waypoint>3354.579 -5248.47 389.7514</Waypoint>
  <Waypoint>3379.148 -5305.874 367.9463</Waypoint>
  <Waypoint>3402.638 -5359.331 345.5158</Waypoint>
  <Waypoint>3408.545 -5420.368 325.6335</Waypoint>
  <Waypoint>3372.693 -5470.632 316.0043</Waypoint>
  <Waypoint>3332.904 -5519.891 303.3512</Waypoint>
  <Waypoint>3292.605 -5568 291.5472</Waypoint>
  <Waypoint>3240.843 -5605.557 290.3982</Waypoint>
  <Waypoint>3187.447 -5640.625 298.4117</Waypoint>
  <Waypoint>3134.025 -5675.711 306.4292</Waypoint>
  <Waypoint>3080.867 -5710.623 314.407</Waypoint>
  <Waypoint>3027.154 -5745.899 322.4681</Waypoint>
  <Waypoint>2974.179 -5782.514 327.2871</Waypoint>
  <Waypoint>2917.278 -5803.397 346.4462</Waypoint>
  <Waypoint>2875.227 -5774.562 377.9259</Waypoint>
  <Waypoint>2870.925 -5721.731 412.5789</Waypoint>
  <Waypoint>2868.124 -5673.816 454.4894</Waypoint>
  <Waypoint>2859.863 -5627.641 498.6533</Waypoint>
  <Waypoint>2867.286 -5582.587 543.5344</Waypoint>
  <Waypoint>2881.685 -5531.65 575.9948</Waypoint>
  <Waypoint>2895.198 -5470.083 587.9619</Waypoint>
  <Waypoint>2906.897 -5416.484 598.3067</Waypoint>
  <Waypoint>2908.78 -5353.011 605.4702</Waypoint>
  <Waypoint>2893.226 -5290.729 605.5273</Waypoint>
  <Waypoint>2876.41 -5229.054 599.9774</Waypoint>
  <Waypoint>2862.981 -5166.276 589.4762</Waypoint>
  <Waypoint>2852.643 -5104.239 577.9012</Waypoint>
  <Waypoint>2860.686 -5041.303 577.5052</Waypoint>
  <Waypoint>2887.709 -4988.108 562.2087</Waypoint>
  <Waypoint>2917.391 -4940.102 531.4996</Waypoint>
  <Waypoint>2943.314 -4896.61 504.2472</Waypoint>
  <Waypoint>2986.161 -4853.188 492.9281</Waypoint>
  <Waypoint>3047.279 -4842.04 489.767</Waypoint>
  <Waypoint>3109.801 -4846.469 476.2153</Waypoint>
  <Waypoint>3172.222 -4850.893 462.8087</Waypoint>
  <Waypoint>3238.431 -4860.782 444.5288</Waypoint>
  <Waypoint>3283.243 -4870.064 418.8477</Waypoint>
  <Waypoint>3338.031 -4881.414 387.4493</Waypoint>
  <Waypoint>3396.559 -4894.336 364.0789</Waypoint>
  <Waypoint>3455.993 -4904.998 343.8697</Waypoint>
  <Waypoint>3516.44 -4905.892 322.1239</Waypoint>
  <Waypoint>3572.476 -4884.7 302.6111</Waypoint>
  <Waypoint>3596.413 -4826.874 289.226</Waypoint>
  <Waypoint>3612.657 -4764.965 286.6216</Waypoint>
  <Waypoint>3626.586 -4702.423 292.1506</Waypoint>
  <Waypoint>3645.183 -4640.912 289.8246</Waypoint>
  <Waypoint>3663.36 -4580.191 279.8999</Waypoint>
  <Waypoint>3693.308 -4522.211 265.8505</Waypoint>
  <Waypoint>3753.151 -4514.243 267.8903</Waypoint>
  <Waypoint>3815.156 -4519.628 283.5238</Waypoint>
  <Waypoint>3861.643 -4522.28 289.7419</Waypoint>
  <Waypoint>3916.126 -4515.839 316.9193</Waypoint>
  <Waypoint>3971.363 -4489.361 334.9387</Waypoint>
  <Waypoint>4023.068 -4451.915 337.4987</Waypoint>
  <Waypoint>4080.513 -4424.073 343.9359</Waypoint>
  <Waypoint>4142.346 -4412.283 352.932</Waypoint>
  <Waypoint>4204.789 -4421.599 355.0782</Waypoint>
  <Waypoint>4267.704 -4419.408 341.7666</Waypoint>
  <Waypoint>4330.61 -4415.056 328.1485</Waypoint>
  <Waypoint>4392.545 -4413.06 312.6519</Waypoint>
  <Waypoint>4453.527 -4429.688 306.129</Waypoint>
  <Waypoint>4506.03 -4466.619 297.4229</Waypoint>
  <Waypoint>4556.925 -4505.513 293.1909</Waypoint>
  <Waypoint>4614.132 -4531.875 292.1965</Waypoint>
  <Waypoint>4677.211 -4523.483 286.7516</Waypoint>
  <Waypoint>4740.531 -4510.669 280.4261</Waypoint>
  <Waypoint>4773.122 -4459.522 279.9896</Waypoint>
  <Waypoint>4732.864 -4417.445 282.4366</Waypoint>
  <Waypoint>4675.127 -4390.06 283.5042</Waypoint>
  <Waypoint>4617.586 -4360.979 284.0305</Waypoint>
  <Waypoint>4578.257 -4340.556 280.9323</Waypoint>
  <Waypoint>4565.79 -4324.918 279.963</Waypoint>
  <Waypoint>4551.214 -4299.647 277.5843</Waypoint>
  <Waypoint>4505.658 -4262.129 272.7175</Waypoint>
  <Waypoint>4464.338 -4299.917 265.3241</Waypoint>
  <Waypoint>4488.646 -4356.289 266.6676</Waypoint>
  <Waypoint>4526.212 -4409.428 269.3666</Waypoint>
  <Waypoint>4565.085 -4460.222 272.3054</Waypoint>
  <Waypoint>4612.487 -4503.3 275.2732</Waypoint>
  <Waypoint>4663.828 -4541.922 278.4711</Waypoint>
  <Waypoint>4722.739 -4559.803 287.5965</Waypoint>
  <Waypoint>4783.518 -4552.006 306.2989</Waypoint>
  <Waypoint>4824.324 -4541.176 348.1277</Waypoint>
  <Waypoint>4837.063 -4531.775 367.1549</Waypoint>
  <Waypoint>4888.265 -4528.417 379.2584</Waypoint>
  <Waypoint>4928.02 -4571.99 360.9199</Waypoint>
  <Waypoint>4958.838 -4624.27 341.4069</Waypoint>
  <Waypoint>4977.742 -4666.273 327.5806</Waypoint>
  <Waypoint>4985.332 -4701.833 334.9793</Waypoint>
  <Waypoint>5017.519 -4756.206 344.3231</Waypoint>
  <Waypoint>5059.026 -4804.824 350.3395</Waypoint>
  <Waypoint>5103.947 -4850.257 353.7893</Waypoint>
  <Waypoint>5130.891 -4870.296 365.8286</Waypoint>
  <Waypoint>5151.075 -4870.824 373.8008</Waypoint>
  <Waypoint>5170.425 -4824.187 382.143</Waypoint>
  <Waypoint>5166.65 -4760.942 380.23</Waypoint>
  <Waypoint>5159.612 -4698.209 370.8222</Waypoint>
  <Waypoint>5161.349 -4634.785 375.7889</Waypoint>
  <Waypoint>5197.559 -4586.738 395.8565</Waypoint>
  <Waypoint>5257.819 -4578.957 414.3362</Waypoint>
  <Waypoint>5311.228 -4611.792 417.0844</Waypoint>
  <Waypoint>5322.403 -4671.616 407.9031</Waypoint>
  <Waypoint>5299.344 -4731.65 399.2303</Waypoint>
  <Waypoint>5261.311 -4782.905 394.9801</Waypoint>
  <Waypoint>5212.15 -4823.371 399.1013</Waypoint>
  <Waypoint>5153.122 -4846.619 400.0964</Waypoint>
  <Waypoint>5089.727 -4857.679 402.0625</Waypoint>
  <Waypoint>5026.52 -4868.714 403.9633</Waypoint>
  <Waypoint>4963.452 -4885.598 399.2438</Waypoint>
  <Waypoint>4903.98 -4900.906 383.8663</Waypoint>
  <Waypoint>4854.714 -4926.802 360.1839</Waypoint>
  <Waypoint>4865.606 -4985.402 359.7505</Waypoint>
  <Waypoint>4904.703 -5009.521 378.3043</Waypoint>
  <Waypoint>4957.128 -5035.292 351.3243</Waypoint>
  <Waypoint>5017.542 -5048.111 342.2555</Waypoint>
  <Waypoint>5077.857 -5042.413 342.0439</Waypoint>
  <Waypoint>5138.84 -5036.652 341.83</Waypoint>
  <Waypoint>5202.937 -5030.597 341.6052</Waypoint>
  <Waypoint>5267.002 -5024.544 341.3805</Waypoint>
  <Waypoint>5322.474 -5018.458 341.3476</Waypoint>
  <Waypoint>5374.3 -4982.811 340.7776</Waypoint>
  <Waypoint>5423.014 -4940.544 339.3702</Waypoint>
  <Waypoint>5471.678 -4897.98 338.0155</Waypoint>
  <Waypoint>5506.282 -4844.565 346.4026</Waypoint>
  <Waypoint>5496.014 -4791.102 377.3273</Waypoint>
  <Waypoint>5447.078 -4770.616 405.9789</Waypoint>
  <Waypoint>5383.62 -4766.914 394.3255</Waypoint>
  <Waypoint>5319.908 -4751.348 382.2883</Waypoint>
  <Waypoint>5260.431 -4735.702 371.1698</Waypoint>
  <Waypoint>5209.11 -4697.597 371.9356</Waypoint>
  <Waypoint>5172.714 -4644.912 372.1529</Waypoint>
  <Waypoint>5144.699 -4587.143 369.5742</Waypoint>
  <Waypoint>5118.114 -4531.803 367.1081</Waypoint>
  <Waypoint>5094.318 -4471.979 363.461</Waypoint>
  <Waypoint>5052.411 -4426.03 353.1835</Waypoint>
  <Waypoint>4992.963 -4428.528 330.5097</Waypoint>
  <Waypoint>4977.118 -4372.069 324.676</Waypoint>
  <Waypoint>4939.709 -4319.61 323.9998</Waypoint>
  <Waypoint>4900.095 -4269.205 326.2831</Waypoint>
  <Waypoint>4839.699 -4250.489 327.5382</Waypoint>
  <Waypoint>4777.354 -4246.081 319.7563</Waypoint>
  <Waypoint>4715.967 -4240.029 301.4258</Waypoint>
  <Waypoint>4654.763 -4233.997 283.1499</Waypoint>
  <Waypoint>4593.632 -4226.942 265.2385</Waypoint>
  <Waypoint>4530.747 -4216.753 251.0017</Waypoint>
  <Waypoint>4467.737 -4209.372 253.3613</Waypoint>
  <Waypoint>4406.125 -4218.997 265.9304</Waypoint>
  <Waypoint>4346.611 -4241.561 275.001</Waypoint>
  <Waypoint>4289.366 -4264.174 292.0434</Waypoint>
  <Waypoint>4232.283 -4286.518 313.1438</Waypoint>
  <Waypoint>4172.59 -4306.444 325.6942</Waypoint>
  <Waypoint>4110.271 -4312.817 336.3421</Waypoint>
  <Waypoint>4046.487 -4320.361 331.0614</Waypoint>
  <Waypoint>3983.144 -4327.854 325.8173</Waypoint>
  <Waypoint>3919.372 -4334.741 320.4219</Waypoint>
  <Waypoint>3855.221 -4334.005 315.6604</Waypoint>
  <Waypoint>3791.323 -4332.741 312.9685</Waypoint>
  <Waypoint>3727.55 -4339.021 311.5356</Waypoint>
  <Waypoint>3672.732 -4368.916 305.2912</Waypoint>
  <Waypoint>3638.07 -4423.138 297.4208</Waypoint>
  <Waypoint>3609.279 -4479.955 290.2886</Waypoint>
  <Waypoint>3587.826 -4540.52 293.0182</Waypoint>
  <Waypoint>3565.339 -4600.357 301.9601</Waypoint>
  <Waypoint>3534.073 -4656.1 309.3925</Waypoint>
  <Waypoint>3501.735 -4711.171 316.2238</Waypoint>
  <Waypoint>3449.015 -4745.392 322.9975</Waypoint>
  <Waypoint>3388.329 -4732.207 329.8322</Waypoint>
  <Waypoint>3335.972 -4709.252 336.2769</Waypoint>
  <Waypoint>3298.303 -4656.331 340.8867</Waypoint>
  <Waypoint>3288.316 -4593.192 337.7058</Waypoint>
  <Waypoint>3314.451 -4538.791 326.7406</Waypoint>
  <Waypoint>3353.005 -4487.613 322.5068</Waypoint>
  <Waypoint>3389.925 -4435.522 315.5707</Waypoint>
  <Waypoint>3428.073 -4383.93 309.0393</Waypoint>
  <Waypoint>3474.874 -4340.516 302.4339</Waypoint>
  <Waypoint>3529.815 -4309.993 294.1529</Waypoint>
  <Waypoint>3588.347 -4290.816 277.6767</Waypoint>
  <Waypoint>3648.857 -4268.041 273.8763</Waypoint>
  <Waypoint>3704.108 -4237.403 281.6103</Waypoint>
  <Waypoint>3722.751 -4211.753 291.1682</Waypoint>
  <Waypoint>3731.497 -4200.063 295.4578</Waypoint>
  <Waypoint>3771.584 -4155.472 316.7569</Waypoint>
  <Waypoint>3821.854 -4117.9 327.1046</Waypoint>
  <Waypoint>3882.08 -4099.347 312.4256</Waypoint>
  <Waypoint>3945.928 -4100.145 303.989</Waypoint>
  <Waypoint>4009.656 -4106.104 298.214</Waypoint>
  <Waypoint>4062.744 -4108.229 284.337</Waypoint>
  <Waypoint>4068.804 -4106.505 284.8274</Waypoint>
  <Waypoint>4095.945 -4100.073 288.7419</Waypoint>
  <Waypoint>4159.795 -4095.597 293.6523</Waypoint>
  <Waypoint>4223.223 -4093.858 286.4983</Waypoint>
  <Waypoint>4286.034 -4092.973 273.6036</Waypoint>
  <Waypoint>4349.502 -4092.079 260.5742</Waypoint>
  <Waypoint>4412.407 -4091.193 247.6603</Waypoint>
  <Waypoint>4475.223 -4090.811 237.4049</Waypoint>
  <Waypoint>4539.106 -4084.47 232.4015</Waypoint>
  <Waypoint>4599.504 -4066.45 240.5156</Waypoint>
  <Waypoint>4654.22 -4036.843 262.5348</Waypoint>
  <Waypoint>4685.222 -4014.642 311.7847</Waypoint>
  <Waypoint>4705.371 -4003.403 371.6102</Waypoint>
  <Waypoint>4733.352 -3998.572 428.7617</Waypoint>
  <Waypoint>4776.708 -3988.364 473.218</Waypoint>
  <Waypoint>4828.342 -3963.274 487.6371</Waypoint>
  <Waypoint>4846.644 -3908.224 473.8855</Waypoint>
  <Waypoint>4826.064 -3853.13 448.7329</Waypoint>
  <Waypoint>4769.577 -3837.449 431.3453</Waypoint>
  <Waypoint>4708.048 -3836.865 412.1805</Waypoint>
  <Waypoint>4646.641 -3836.266 392.954</Waypoint>
  <Waypoint>4585.059 -3834.947 372.6377</Waypoint>
  <Waypoint>4522.709 -3835.812 362.7477</Waypoint>
  <Waypoint>4458.398 -3839.518 362.7705</Waypoint>
  <Waypoint>4395.535 -3847.573 354.493</Waypoint>
  <Waypoint>4332.471 -3856.153 345.2081</Waypoint>
  <Waypoint>4269.82 -3847.702 338.4932</Waypoint>
  <Waypoint>4228.989 -3801.967 333.7827</Waypoint>
  <Waypoint>4250.664 -3742.914 338.5279</Waypoint>
  <Waypoint>4294.626 -3698.855 339.0337</Waypoint>
  <Waypoint>4323.898 -3707.237 337.6804</Waypoint>
  <Waypoint>4345.775 -3726.416 335.9774</Waypoint>
  <Waypoint>4398.638 -3762 333.2686</Waypoint>
  <Waypoint>4454.404 -3792.767 331.5026</Waypoint>
  <Waypoint>4512.083 -3821.682 325.9973</Waypoint>
  <Waypoint>4557.832 -3862.702 322.8577</Waypoint>
  <Waypoint>4610.398 -3889.143 339.7352</Waypoint>
  <Waypoint>4666.771 -3872.548 361.8633</Waypoint>
  <Waypoint>4687.77 -3818.329 378.8277</Waypoint>
  <Waypoint>4689.405 -3755.792 392.0126</Waypoint>
  <Waypoint>4687.759 -3691.335 390.8182</Waypoint>
  <Waypoint>4659.961 -3638.482 371.6499</Waypoint>
  <Waypoint>4618.043 -3596.689 347.2296</Waypoint>
  <Waypoint>4571.023 -3555.817 332.1652</Waypoint>
  <Waypoint>4515.311 -3526.685 329.1656</Waypoint>
  <Waypoint>4454.271 -3516.345 331.9284</Waypoint>
  <Waypoint>4398.136 -3547.777 335.575</Waypoint>
  <Waypoint>4348.467 -3585.944 323.0264</Waypoint>
  <Waypoint>4344.451 -3596.764 320.6155</Waypoint>
  <Waypoint>4348.484 -3603.61 320.8097</Waypoint>
  <Waypoint>4379.488 -3656.683 323.0211</Waypoint>
  <Waypoint>4411.948 -3711.558 330.6788</Waypoint>
  <Waypoint>4435.866 -3770.336 326.9824</Waypoint>
  <Waypoint>4423.593 -3832.753 319.7162</Waypoint>
  <Waypoint>4388.793 -3886.537 315.1376</Waypoint>
  <Waypoint>4350.898 -3939.561 307.1077</Waypoint>
  <Waypoint>4305.11 -3982.02 299.4231</Waypoint>
  <Waypoint>4246.198 -4003.897 288.6429</Waypoint>
  <Waypoint>4184.005 -4010.934 275.466</Waypoint>
  <Waypoint>4121.284 -4017.118 263.3029</Waypoint>
  <Waypoint>4058.063 -4023.932 251.9272</Waypoint>
  <Waypoint>3994.044 -4024.842 244.107</Waypoint>
  <Waypoint>3931.709 -4010.778 250.8713</Waypoint>
  <Waypoint>3869.198 -3995.141 258.5547</Waypoint>
  <Waypoint>3808.409 -3979.935 266.0265</Waypoint>
  <Waypoint>3746.759 -3964.513 273.6041</Waypoint>
  <Waypoint>3683.941 -3948.8 281.3253</Waypoint>
  <Waypoint>3622.969 -3931.166 289.9696</Waypoint>
  <Waypoint>3575.978 -3890.587 301.3079</Waypoint>
  <Waypoint>3545.208 -3835.332 314.2673</Waypoint>
  <Waypoint>3517.589 -3779.832 328.6931</Waypoint>
  <Waypoint>3487.252 -3726.466 347.4831</Waypoint>
  <Waypoint>3449.124 -3686.812 378.7066</Waypoint>
  <Waypoint>3406.407 -3667.371 422.886</Waypoint>
  <Waypoint>3363.181 -3663.309 470.1848</Waypoint>
  <Waypoint>3321.494 -3666.654 519.0385</Waypoint>
  <Waypoint>3286.207 -3676.32 572.03</Waypoint>
  <Waypoint>3251.816 -3698.521 621.0649</Waypoint>
  <Waypoint>3222.68 -3729.674 669.4139</Waypoint>
  <Waypoint>3195.721 -3762.456 718.1181</Waypoint>
  <Waypoint>3173.14 -3799.379 764.6559</Waypoint>
  <Waypoint>3161.85 -3855.588 790.7248</Waypoint>
  <Waypoint>3137.41 -3905.916 797.9183</Waypoint>
  <Waypoint>3081.633 -3926.176 791.6314</Waypoint>
  <Waypoint>3054.718 -3872.142 777.4807</Waypoint>
  <Waypoint>3070.898 -3815.246 753.901</Waypoint>
  <Waypoint>3118.159 -3780.183 729.6296</Waypoint>
  <Waypoint>3174.433 -3774.65 704.8962</Waypoint>
  <Waypoint>3232.754 -3791.487 683.8431</Waypoint>
  <Waypoint>3261.405 -3835.336 651.9361</Waypoint>
  <Waypoint>3276.233 -3873.407 623.7507</Waypoint>
  <Waypoint>3292.289 -3922.869 586.2796</Waypoint>
  <Waypoint>3303.268 -3975.122 549.8138</Waypoint>
  <Waypoint>3311.807 -4028.379 514.5582</Waypoint>
  <Waypoint>3319.886 -4081.784 479.9952</Waypoint>
  <Waypoint>3315.684 -4137.482 456.644</Waypoint>
  <Waypoint>3290.588 -4196.479 449.7921</Waypoint>
  <Waypoint>3265.71 -4254.951 443.0146</Waypoint>
  <Waypoint>3216.755 -4284.751 440.1465</Waypoint>
  <Waypoint>3153.349 -4291.646 435.6864</Waypoint>
  <Waypoint>3089.381 -4297.939 432.3334</Waypoint>
  <Waypoint>3035.391 -4278.015 452.4897</Waypoint>
  <Waypoint>3015.661 -4227.491 485.5375</Waypoint>
  <Waypoint>3023.22 -4176.024 522.0595</Waypoint>
  <Waypoint>3045.9 -4130.716 562.177</Waypoint>
  <Waypoint>3058.332 -4082.954 602.0161</Waypoint>
  <Waypoint>3043.637 -4033.419 639.7291</Waypoint>
  <Waypoint>3005.443 -3990.388 670.0233</Waypoint>
  <Waypoint>2981.502 -3929.211 675.0071</Waypoint>
  <Waypoint>2971.354 -3871.976 655.107</Waypoint>
  <Waypoint>2973.133 -3814.689 626.1896</Waypoint>
  <Waypoint>2982.105 -3758.624 595.2326</Waypoint>
  <Waypoint>2991.019 -3702.918 564.4742</Waypoint>
  <Waypoint>3000.319 -3645.809 535.0633</Waypoint>
  <Waypoint>3018.469 -3585.907 528.256</Waypoint>
  <Waypoint>3060.046 -3537.106 526.192</Waypoint>
  <Waypoint>3108.028 -3503.495 506.1781</Waypoint>
  <Waypoint>3149.299 -3475.543 477.2832</Waypoint>
  <Waypoint>3195.853 -3444.014 444.6904</Waypoint>
  <Waypoint>3241.72 -3412.949 412.5779</Waypoint>
  <Waypoint>3288.067 -3381.56 380.1291</Waypoint>
  <Waypoint>3334.749 -3349.428 349.2926</Waypoint>
  <Waypoint>3380.882 -3314.962 322.1544</Waypoint>
  <Waypoint>3440.575 -3293.745 310.1345</Waypoint>
  <Waypoint>3501.034 -3274.172 308.8207</Waypoint>
  <Waypoint>3559.971 -3286.043 328.8014</Waypoint>
  <Waypoint>3614.052 -3308.553 354.3577</Waypoint>
  <Waypoint>3667.623 -3331.284 380.7543</Waypoint>
  <Waypoint>3725.584 -3356.967 393.472</Waypoint>
  <Waypoint>3788.305 -3367.752 394.22</Waypoint>
  <Waypoint>3849.305 -3382.917 381.0124</Waypoint>
  <Waypoint>3909.395 -3399.785 366.8527</Waypoint>
  <Waypoint>3965.313 -3429.61 362.8873</Waypoint>
  <Waypoint>4013.683 -3471.892 358.2647</Waypoint>
  <Waypoint>4061.756 -3514.075 352.7816</Waypoint>
  <Waypoint>4110.223 -3556.63 347.2522</Waypoint>
  <Waypoint>4163.955 -3591.008 343.752</Waypoint>
  <Waypoint>4224.366 -3611.491 345.0723</Waypoint>
  <Waypoint>4284.572 -3597.021 352.7922</Waypoint>
  <Waypoint>4339.261 -3565.943 356.4741</Waypoint>
  <Waypoint>4394.864 -3534.345 360.2176</Waypoint>
  <Waypoint>4450.386 -3502.148 363.0003</Waypoint>
  <Waypoint>4506.004 -3469.569 364.4781</Waypoint>
  <Waypoint>4568.445 -3458.984 366.1086</Waypoint>
  <Waypoint>4614.108 -3501.196 367.3626</Waypoint>
  <Waypoint>4631.395 -3561.376 362.2182</Waypoint>
  <Waypoint>4606.407 -3618.296 354.5773</Waypoint>
  <Waypoint>4546.017 -3639.394 343.6516</Waypoint>
  <Waypoint>4489.081 -3624.284 326.2086</Waypoint>
  <Waypoint>4435.802 -3591.479 317.6244</Waypoint>
  <Waypoint>4375.09 -3586.718 322.2462</Waypoint>
  <Waypoint>4315.553 -3610.498 323.7418</Waypoint>
  <Waypoint>4260.63 -3641.141 333.9281</Waypoint>
  <Waypoint>4203.754 -3672.875 344.4768</Waypoint>
  <Waypoint>4148.574 -3702.413 354.2415</Waypoint>
  <Waypoint>4091.658 -3727.014 352.8798</Waypoint>
  <Waypoint>4034.428 -3746.758 330.7849</Waypoint>
  <Waypoint>3977.084 -3766.541 308.6462</Waypoint>
  <Waypoint>3928.697 -3783.234 289.9656</Waypoint>
  <Waypoint>3874.386 -3801.971 268.9979</Waypoint>
  <Waypoint>3816.015 -3821.388 250.7955</Waypoint>
  <Waypoint>3754.057 -3839.368 245.0271</Waypoint>
  <Waypoint>3690.612 -3850.445 248.4936</Waypoint>
  <Waypoint>3629.031 -3843.308 257.8078</Waypoint>
  <Waypoint>3587.061 -3799.845 276.2852</Waypoint>
  <Waypoint>3560.801 -3744.497 294.2482</Waypoint>
  <Waypoint>3535.087 -3686.329 309.9054</Waypoint>
  <Waypoint>3517.358 -3629.564 331.4462</Waypoint>
  <Waypoint>3489.335 -3580.113 346.3715</Waypoint>
  <Waypoint>3439.573 -3538.814 345.7506</Waypoint>
  <Waypoint>3390.057 -3497.719 345.1328</Waypoint>
  <Waypoint>3340.541 -3456.624 344.515</Waypoint>
  <Waypoint>3291.295 -3415.753 343.9006</Waypoint>
  <Waypoint>3241.337 -3374.292 343.2773</Waypoint>
  <Waypoint>3191.551 -3332.972 342.6561</Waypoint>
  <Waypoint>3136.311 -3304.683 333.5991</Waypoint>
  <Waypoint>3077.653 -3282.148 320.6432</Waypoint>
  <Waypoint>3018.616 -3259.468 307.6035</Waypoint>
  <Waypoint>2961.038 -3237.348 294.886</Waypoint>
  <Waypoint>2901.826 -3214.6 281.8076</Waypoint>
  <Waypoint>2843.139 -3192.054 268.8453</Waypoint>
  <Waypoint>2784.569 -3169.553 255.9087</Waypoint>
  <Waypoint>2727.466 -3147.636 243.3791</Waypoint>
  <Waypoint>2666.807 -3128.743 238.7932</Waypoint>
  <Waypoint>2603.556 -3118.671 240.9481</Waypoint>
  <Waypoint>2539.611 -3103.598 240.5783</Waypoint>
  <Waypoint>2500.018 -3060.21 222.6662</Waypoint>
  <Waypoint>2485.066 -3004.894 194.4145</Waypoint>
  <Waypoint>2494.196 -2947.731 166.9811</Waypoint>
  <Waypoint>2524.685 -2895.662 151.3648</Waypoint>
  <Waypoint>2586.682 -2892.241 153.3335</Waypoint>
  <Waypoint>2644.738 -2909.293 160.4754</Waypoint>
  <Waypoint>2678.95 -2918.71 163.9546</Waypoint>
  <Waypoint>2738.584 -2935.123 170.0191</Waypoint>
  <Waypoint>2800.784 -2950.503 176.6723</Waypoint>
  <Waypoint>2863.994 -2959.065 172.661</Waypoint>
  <Waypoint>2927.583 -2967.336 172.9866</Waypoint>
  <Waypoint>2991.781 -2974.794 175.0632</Waypoint>
  <Waypoint>3054.59 -2983.894 186.2887</Waypoint>
  <Waypoint>3112.722 -2995.705 209.3576</Waypoint>
  <Waypoint>3170.516 -3008.004 234.4391</Waypoint>
  <Waypoint>3228.784 -3020.404 258.363</Waypoint>
  <Waypoint>3289.166 -3032.602 275.2292</Waypoint>
  <Waypoint>3351.508 -3033.806 290.1004</Waypoint>
  <Waypoint>3414.331 -3026.025 304.6921</Waypoint>
  <Waypoint>3474.481 -3010.517 319.8863</Waypoint>
  <Waypoint>3530.169 -2995.032 347.3654</Waypoint>
  <Waypoint>3593.154 -2986.407 352.5665</Waypoint>
  <Waypoint>3656.872 -2982.498 349.6818</Waypoint>
  <Waypoint>3720.932 -2978.567 346.5953</Waypoint>
  <Waypoint>3785.314 -2977.744 349.056</Waypoint>
  <Waypoint>3849.474 -2979.356 354.1634</Waypoint>
  <Waypoint>3912.712 -2987.817 357.7814</Waypoint>
  <Waypoint>3972.579 -3010.796 359.4411</Waypoint>
  <Waypoint>4026.251 -3045.869 361.0625</Waypoint>
  <Waypoint>4078.292 -3082.846 362.9111</Waypoint>
  <Waypoint>4136.401 -3108.926 369.3955</Waypoint>
  <Waypoint>4198.767 -3118.913 379.9209</Waypoint>
  <Waypoint>4261.677 -3112.851 390.7261</Waypoint>
  <Waypoint>4320.33 -3085.524 398.7809</Waypoint>
  <Waypoint>4368.432 -3043.83 404.0441</Waypoint>
  <Waypoint>4390.876 -2984.687 405.4165</Waypoint>
  <Waypoint>4379.603 -2922.506 400.6735</Waypoint>
  <Waypoint>4357.597 -2862.568 392.6639</Waypoint>
  <Waypoint>4329.199 -2805.252 383.7129</Waypoint>
  <Waypoint>4275.555 -2779.342 374.8318</Waypoint>
  <Waypoint>4212.619 -2778.552 363.6202</Waypoint>
  <Waypoint>4149.29 -2777.942 352.0383</Waypoint>
  <Waypoint>4086.75 -2778.228 339.0974</Waypoint>
  <Waypoint>4023.844 -2778.69 325.856</Waypoint>
  <Waypoint>3960.829 -2778.257 312.3725</Waypoint>
  <Waypoint>3898.176 -2779.604 299.316</Waypoint>
  <Waypoint>3840.178 -2804.789 292.1589</Waypoint>
  <Waypoint>3787.643 -2841.786 293.3643</Waypoint>
  <Waypoint>3750.294 -2890.759 310.3362</Waypoint>
  <Waypoint>3709.34 -2938.539 323.0096</Waypoint>
  <Waypoint>3648.507 -2947.85 317.611</Waypoint>
  <Waypoint>3590.941 -2921.819 308.7668</Waypoint>
  <Waypoint>3536.528 -2889.205 298.5564</Waypoint>
  <Waypoint>3486.047 -2850.072 288.9987</Waypoint>
  <Waypoint>3429.501 -2821.451 281.2885</Waypoint>
  <Waypoint>3371.888 -2793.953 273.45</Waypoint>
  <Waypoint>3314.675 -2766.646 265.6659</Waypoint>
  <Waypoint>3257.269 -2738.756 254.8049</Waypoint>
  <Waypoint>3200.754 -2714.281 238.3091</Waypoint>
  <Waypoint>3141.008 -2697.724 219.0927</Waypoint>
  <Waypoint>3080.232 -2683.188 206.7417</Waypoint>
  <Waypoint>3018.259 -2666.39 203.6013</Waypoint>
  <Waypoint>2956.131 -2649.551 200.453</Waypoint>
  <Waypoint>2894.929 -2631.524 194.5403</Waypoint>
  <Waypoint>2837.514 -2608.948 173.1164</Waypoint>
  <Waypoint>2781.923 -2587.089 152.3731</Waypoint>
  <Waypoint>2725.209 -2564.789 131.2109</Waypoint>
  <Waypoint>2668.795 -2542.998 109.9036</Waypoint>
  <Waypoint>2612.445 -2519.897 90.33778</Waypoint>
  <Waypoint>2562.136 -2482.622 78.32844</Waypoint>
  <Waypoint>2548.817 -2423.186 75.16248</Waypoint>
  <Waypoint>2594.043 -2380.482 78.44592</Waypoint>
  <Waypoint>2654.538 -2359.219 82.44151</Waypoint>
  <Waypoint>2717.923 -2351.884 90.05051</Waypoint>
  <Waypoint>2781.159 -2344.472 97.42815</Waypoint>
  <Waypoint>2844.5 -2351.131 99.75993</Waypoint>
  <Waypoint>2894.663 -2380.345 106.8273</Waypoint>
  <Waypoint>2948.313 -2411.902 115.0769</Waypoint>
  <Waypoint>3003.545 -2444.388 123.5697</Waypoint>
  <Waypoint>3058.449 -2476.683 132.0121</Waypoint>
  <Waypoint>3100.344 -2501.325 138.4541</Waypoint>
  <Waypoint>3155.4 -2533.409 145.9012</Waypoint>
  <Waypoint>3213.955 -2558.762 142.4377</Waypoint>
  <Waypoint>3277.99 -2564.036 139.6115</Waypoint>
  <Waypoint>3339.352 -2560.898 151.2983</Waypoint>
  <Waypoint>3396.486 -2547.275 177.5104</Waypoint>
  <Waypoint>3454.473 -2534.959 202.1433</Waypoint>
  <Waypoint>3515.465 -2527.643 219.2976</Waypoint>
  <Waypoint>3578.621 -2530.381 227.7755</Waypoint>
  <Waypoint>3642.492 -2538.038 231.4705</Waypoint>
  <Waypoint>3705.315 -2535.62 242.3141</Waypoint>
  <Waypoint>3760.075 -2531.829 255.695</Waypoint>
  <Waypoint>3811.494 -2528.268 268.2594</Waypoint>
  <Waypoint>3873.957 -2523.943 283.5227</Waypoint>
  <Waypoint>3938.4 -2519.481 299.2699</Waypoint>
  <Waypoint>3998.812 -2516.262 312.8692</Waypoint>
  <Waypoint>4062.198 -2511.081 319.9</Waypoint>
  <Waypoint>4125.87 -2501.959 319.7722</Waypoint>
  <Waypoint>4189.579 -2492.299 318.3223</Waypoint>
  <Waypoint>4252.203 -2500.949 323.9358</Waypoint>
  <Waypoint>4313.952 -2517.685 325.6669</Waypoint>
  <Waypoint>4376.563 -2534.653 327.4221</Waypoint>
  <Waypoint>4438.097 -2550.734 331.5195</Waypoint>
  <Waypoint>4500.324 -2561.481 349.8978</Waypoint>
  <Waypoint>4562.28 -2556.07 360.5076</Waypoint>
  <Waypoint>4621.421 -2531.919 358.1162</Waypoint>
  <Waypoint>4644.134 -2477.036 340.1149</Waypoint>
  <Waypoint>4639.168 -2416.417 319.8321</Waypoint>
  <Waypoint>4629.183 -2356.66 298.1743</Waypoint>
  <Waypoint>4609.46 -2296.761 287.2449</Waypoint>
  <Waypoint>4581.319 -2239.062 278.2036</Waypoint>
  <Waypoint>4548.346 -2185.057 281.5014</Waypoint>
  <Waypoint>4483.611 -2159.422 285.893</Waypoint>
  <Waypoint>4433.937 -2178.881 286.5518</Waypoint>
  <Waypoint>4381.826 -2216.39 288.3028</Waypoint>
  <Waypoint>4332.738 -2254.699 299.9037</Waypoint>
  <Waypoint>4279.27 -2288.917 308.0613</Waypoint>
  <Waypoint>4224.882 -2322.421 312.4721</Waypoint>
  <Waypoint>4170.603 -2355.858 316.8741</Waypoint>
  <Waypoint>4115.754 -2389.646 321.3223</Waypoint>
  <Waypoint>4059.555 -2423.282 326.3433</Waypoint>
  <Waypoint>4000.713 -2442.064 316.9162</Waypoint>
  <Waypoint>3937.566 -2433.406 304.0708</Waypoint>
  <Waypoint>3894.474 -2390.918 292.2627</Waypoint>
  <Waypoint>3871.336 -2332.31 279.2038</Waypoint>
  <Waypoint>3849.379 -2273.839 265.1371</Waypoint>
  <Waypoint>3820.779 -2218.181 251.444</Waypoint>
  <Waypoint>3815.942 -2155.422 247.3108</Waypoint>
  <Waypoint>3827.36 -2092.22 250.3271</Waypoint>
  <Waypoint>3843.208 -2029.693 252.7451</Waypoint>
  <Waypoint>3848.836 -1970.044 252.7126</Waypoint>
  <Waypoint>3830.054 -1954.084 254.3403</Waypoint>
  <Waypoint>3819.177 -1949.633 255.1053</Waypoint>
  <Waypoint>3803.965 -1944.861 255.8293</Waypoint>
  <Waypoint>3743.021 -1925.642 258.7129</Waypoint>
  <Waypoint>3680.475 -1911.574 258.4701</Waypoint>
  <Waypoint>3617.204 -1917.651 252.2505</Waypoint>
  <Waypoint>3553.876 -1929.111 246.5319</Waypoint>
  <Waypoint>3493.042 -1948.737 241.946</Waypoint>
  <Waypoint>3436.257 -1977.833 243.4235</Waypoint>
  <Waypoint>3381.269 -2010.93 248.8046</Waypoint>
  <Waypoint>3326.727 -2044.529 254.5602</Waypoint>
  <Waypoint>3273.2 -2079.353 257.5925</Waypoint>
  <Waypoint>3220.306 -2116.106 254.2284</Waypoint>
  <Waypoint>3168.532 -2155.125 245.4712</Waypoint>
  <Waypoint>3131.886 -2206.126 238.9077</Waypoint>
  <Waypoint>3106.798 -2264.188 231.8415</Waypoint>
  <Waypoint>3086.173 -2324.127 219.9485</Waypoint>
  <Waypoint>3045.883 -2370.03 205.1097</Waypoint>
  <Waypoint>2987.14 -2389.657 190.7065</Waypoint>
  <Waypoint>2924.808 -2396.342 176.8049</Waypoint>
  <Waypoint>2862.397 -2397.514 162.3952</Waypoint>
  <Waypoint>2799.572 -2398.836 147.9537</Waypoint>
  <Waypoint>2736.672 -2403.263 135.2838</Waypoint>
  <Waypoint>2673.828 -2404.102 122.0415</Waypoint>
  <Waypoint>2617.831 -2378.429 104.9294</Waypoint>
  <Waypoint>2566.825 -2343.609 88.14234</Waypoint>
  <Waypoint>2521.202 -2298.973 86.92451</Waypoint>
  <Waypoint>2515.758 -2238.589 90.68924</Waypoint>
  <Waypoint>2530.848 -2183.101 94.31366</Waypoint>
  <Waypoint>2588.22 -2158.573 98.26547</Waypoint>
  <Waypoint>2649.723 -2161.084 102.0302</Waypoint>
  <Waypoint>2710.461 -2166.642 107.2968</Waypoint>
  <Waypoint>2772.156 -2180.279 120.9259</Waypoint>
  <Waypoint>2833.29 -2193.846 134.288</Waypoint>
  <Waypoint>2892.542 -2207.422 152.9219</Waypoint>
  <Waypoint>2948.072 -2218.371 182.9834</Waypoint>
  <Waypoint>3003.413 -2229.424 213.897</Waypoint>
  <Waypoint>3059.007 -2241.255 243.2404</Waypoint>
  <Waypoint>3115.464 -2253.27 271.6869</Waypoint>
  <Waypoint>3179.574 -2254.783 275.1641</Waypoint>
  <Waypoint>3244.271 -2255.137 275.898</Waypoint>
  <Waypoint>3308.105 -2255.487 276.6221</Waypoint>
  <Waypoint>3372.132 -2255.838 277.3484</Waypoint>
  <Waypoint>3436.765 -2256.192 278.0816</Waypoint>
  <Waypoint>3499.801 -2256.328 278.6544</Waypoint>
  <Waypoint>3563.093 -2257.202 273.1728</Waypoint>
  <Waypoint>3626.859 -2259.667 266.8593</Waypoint>
  <Waypoint>3690.773 -2263.031 260.8524</Waypoint>
  <Waypoint>3753.401 -2259.422 273.1279</Waypoint>
  <Waypoint>3816.357 -2254.814 287.4694</Waypoint>
  <Waypoint>3878.165 -2250.29 301.5493</Waypoint>
  <Waypoint>3941.609 -2243.564 311.5006</Waypoint>
  <Waypoint>4004.374 -2231.917 318.7007</Waypoint>
  <Waypoint>4067 -2220.302 322.0406</Waypoint>
  <Waypoint>4130.917 -2219.81 316.6097</Waypoint>
  <Waypoint>4192.754 -2233.446 312.0708</Waypoint>
  <Waypoint>4251.347 -2259.184 318.1765</Waypoint>
  <Waypoint>4310.318 -2285.087 324.3216</Waypoint>
  <Waypoint>4368.998 -2310.863 330.4364</Waypoint>
  <Waypoint>4428.654 -2336.316 335.0804</Waypoint>
  <Waypoint>4489.914 -2351.373 332.7608</Waypoint>
  <Waypoint>4549.532 -2331.331 325.2777</Waypoint>
  <Waypoint>4582.076 -2279.353 313.3546</Waypoint>
  <Waypoint>4594.442 -2216.483 306.3435</Waypoint>
  <Waypoint>4574.136 -2157.909 298.644</Waypoint>
  <Waypoint>4535.18 -2108.874 289.4678</Waypoint>
  <Waypoint>4497.194 -2056.532 282.381</Waypoint>
  <Waypoint>4453.29 -2010.358 281.3394</Waypoint>
  <Waypoint>4405.066 -1969.04 289.2088</Waypoint>
  <Waypoint>4347.875 -1941.667 298.4443</Waypoint>
  <Waypoint>4286.672 -1927.454 309.3586</Waypoint>
  <Waypoint>4223.032 -1925.186 320.002</Waypoint>
  <Waypoint>4158.943 -1928.75 324.2299</Waypoint>
  <Waypoint>4094.949 -1932.899 327.687</Waypoint>
  <Waypoint>4031.147 -1931.703 328.7092</Waypoint>
  <Waypoint>3967.128 -1928.581 328.765</Waypoint>
  <Waypoint>3902.509 -1925.336 328.9505</Waypoint>
  <Waypoint>3839.67 -1924.129 320.588</Waypoint>
  <Waypoint>3776.64 -1923.533 308.7916</Waypoint>
  <Waypoint>3713.296 -1922.935 296.9365</Waypoint>
  <Waypoint>3650.674 -1922.35 285.3515</Waypoint>
  <Waypoint>3587.415 -1924.827 275.8787</Waypoint>
  <Waypoint>3525.019 -1937.919 267.2241</Waypoint>
  <Waypoint>3463.316 -1967.427 254.2386</Waypoint>
  <Waypoint>3411.458 -1992.227 243.3251</Waypoint>
  <Waypoint>3352.065 -2015.504 230.1018</Waypoint>
  <Waypoint>3290.349 -2009.664 217.1566</Waypoint>
  <Waypoint>3227.805 -2001.162 204.1427</Waypoint>
  <Waypoint>3165.574 -1992.752 191.4855</Waypoint>
  <Waypoint>3106.101 -1992.412 180.2256</Waypoint>
  <Waypoint>3042.654 -1992.699 167.8807</Waypoint>
  <Waypoint>2979.986 -1991.195 154.3697</Waypoint>
  <Waypoint>2916.881 -1989.607 140.3174</Waypoint>
  <Waypoint>2853.185 -1988.005 126.1333</Waypoint>
  <Waypoint>2791.486 -1986.555 112.2163</Waypoint>
  <Waypoint>2728.493 -1985.311 97.63844</Waypoint>
  <Waypoint>2665.225 -1986.943 87.14098</Waypoint>
  <Waypoint>2601.707 -1991.59 81.51295</Waypoint>
  <Waypoint>2537.714 -1996.271 75.84278</Waypoint>
  <Waypoint>2473.979 -1992.203 72.52516</Waypoint>
  <Waypoint>2421.477 -1956.312 74.05582</Waypoint>
  <Waypoint>2398.626 -1897.922 76.89082</Waypoint>
  <Waypoint>2430.133 -1843.844 80.36784</Waypoint>
  <Waypoint>2488.949 -1820.338 85.32916</Waypoint>
  <Waypoint>2552.822 -1817.633 91.40132</Waypoint>
  <Waypoint>2615.431 -1829.933 95.47149</Waypoint>
  <Waypoint>2677.791 -1842.184 99.5254</Waypoint>
  <Waypoint>2740.525 -1854.508 103.6037</Waypoint>
  <Waypoint>2803.684 -1864.486 108.4364</Waypoint>
  <Waypoint>2867.127 -1870.022 115.6138</Waypoint>
  <Waypoint>2929.467 -1873.974 130.8868</Waypoint>
  <Waypoint>2990.872 -1875.946 148.7957</Waypoint>
  <Waypoint>3053.074 -1871.112 165.4992</Waypoint>
  <Waypoint>3115.734 -1863.059 177.4842</Waypoint>
  <Waypoint>3177.601 -1852.706 189.2669</Waypoint>
  <Waypoint>3240.268 -1841.108 200.7809</Waypoint>
  <Waypoint>3302.764 -1829.959 211.8639</Waypoint>
  <Waypoint>3365.349 -1820.587 222.6241</Waypoint>
  <Waypoint>3427.725 -1808.265 233.6748</Waypoint>
  <Waypoint>3488.554 -1792.485 244.1028</Waypoint>
  <Waypoint>3548.506 -1771.264 253.0408</Waypoint>
  <Waypoint>3607.565 -1746.781 261.237</Waypoint>
  <Waypoint>3665.812 -1721.267 268.1157</Waypoint>
  <Waypoint>3726.295 -1700.378 276.0611</Waypoint>
  <Waypoint>3787.444 -1703.271 296.4793</Waypoint>
  <Waypoint>3848.324 -1712.618 313.4806</Waypoint>
  <Waypoint>3910.647 -1726.933 321.7717</Waypoint>
  <Waypoint>3972.748 -1742.366 321.6458</Waypoint>
  <Waypoint>4035.237 -1755.977 314.5163</Waypoint>
  <Waypoint>4091.145 -1784.596 304.8776</Waypoint>
  <Waypoint>4145.45 -1818.879 292.1614</Waypoint>
  <Waypoint>4198.416 -1852.815 281.5534</Waypoint>
  <Waypoint>4254.946 -1883.431 276.2113</Waypoint>
  <Waypoint>4311.448 -1914.032 270.8719</Waypoint>
  <Waypoint>4367.615 -1944.452 265.5642</Waypoint>
  <Waypoint>4423.978 -1974.977 260.2381</Waypoint>
  <Waypoint>4481.48 -2002.768 255.6573</Waypoint>
  <Waypoint>4540.345 -1993.799 263.2727</Waypoint>
  <Waypoint>4549.437 -1931.049 269.1453</Waypoint>
  <Waypoint>4550.661 -1867.573 279.3297</Waypoint>
  <Waypoint>4540.362 -1803.29 285.8916</Waypoint>
  <Waypoint>4500.93 -1755.507 285.7347</Waypoint>
  <Waypoint>4444.253 -1726.525 289.9994</Waypoint>
  <Waypoint>4381.267 -1708.386 297.8152</Waypoint>
  <Waypoint>4321.482 -1691.169 305.5098</Waypoint>
  <Waypoint>4259.688 -1674.086 312.4533</Waypoint>
  <Waypoint>4197.372 -1661.727 314.0571</Waypoint>
  <Waypoint>4133.092 -1660.867 314.4497</Waypoint>
  <Waypoint>4071.695 -1671.04 317.5382</Waypoint>
  <Waypoint>4023.904 -1713.371 322.4506</Waypoint>
  <Waypoint>3975.702 -1755.426 327.3057</Waypoint>
  <Waypoint>3918.657 -1785.171 331.8581</Waypoint>
  <Waypoint>3856.639 -1783.734 320.8882</Waypoint>
  <Waypoint>3793.737 -1777.438 304.3627</Waypoint>
  <Waypoint>3731.542 -1771.212 288.0229</Waypoint>
  <Waypoint>3669.416 -1769.266 273.4236</Waypoint>
  <Waypoint>3607.133 -1767.944 259.0411</Waypoint>
  <Waypoint>3541.523 -1766.552 243.8903</Waypoint>
  <Waypoint>3483.686 -1765.324 230.5346</Waypoint>
  <Waypoint>3421.155 -1763.997 216.0947</Waypoint>
  <Waypoint>3358.892 -1761.829 202.1411</Waypoint>
  <Waypoint>3298.745 -1743.005 190.0407</Waypoint>
  <Waypoint>3241.287 -1719.035 176.973</Waypoint>
  <Waypoint>3180.956 -1709.124 160.4982</Waypoint>
  <Waypoint>3119.099 -1713.405 142.0135</Waypoint>
  <Waypoint>3057.805 -1718.226 124.7221</Waypoint>
  <Waypoint>2994.356 -1726.529 116.4349</Waypoint>
  <Waypoint>2931.721 -1734.841 108.0043</Waypoint>
  <Waypoint>2868.656 -1743.016 99.51427</Waypoint>
  <Waypoint>2804.999 -1736.191 90.75468</Waypoint>
  <Waypoint>2746.01 -1714.269 80.7217</Waypoint>
  <Waypoint>2705.326 -1666.871 80.81604</Waypoint>
  <Waypoint>2730.495 -1610.704 82.49348</Waypoint>
  <Waypoint>2783.406 -1597.474 83.85663</Waypoint>
  <Waypoint>2844.302 -1600.681 85.34689</Waypoint>
  <Waypoint>2908.672 -1604.071 86.92216</Waypoint>
  <Waypoint>2971.832 -1607.397 88.4678</Waypoint>
  <Waypoint>3036.01 -1610.777 90.03839</Waypoint>
  <Waypoint>3099.769 -1614.14 91.75853</Waypoint>
  <Waypoint>3163.555 -1616.162 99.91129</Waypoint>
  <Waypoint>3179.025 -1615.533 101.887</Waypoint>
</GlideProfile>
